[
  {
    "name": "Massachusetts Institute of Technology",
    "slug": "mit",
    "state": "MA",
    "city": "Cambridge",
    "region": "Northeast",
    "csRanking": 5,
    "tuitionInState": 57986,
    "tuitionOutOfState": 57986,
    "roomAndBoard": 18590,
    "acceptanceRate": 0.04,
    "enrollment": 11520,
    "graduationRate": 0.94,
    "medianEarnings6yr": 104700,
    "medianDebt": 12000,
    "website": "https://www.mit.edu",
    "usnewsUrl": "https://www.usnews.com/best-colleges/mit-2178",
    "nicheGrades": {
      "overall": "A+",
      "academics": "A+",
      "value": "A+",
      "diversity": "A",
      "campus": "A",
      "athletics": "B+",
      "partyScene": "B",
      "professors": "A+",
      "location": "A+",
      "dorms": "B+",
      "campusFood": "B",
      "studentLife": "A",
      "safety": "A+"
    },
    "nicheUrl": "https://www.niche.com/colleges/massachusetts-institute-of-technology/"
  },
  {
    "name": "Stanford University",
    "slug": "stanford",
    "state": "CA",
    "city": "Stanford",
    "region": "West",
    "csRanking": 11,
    "tuitionInState": 56169,
    "tuitionOutOfState": 56169,
    "roomAndBoard": 18619,
    "acceptanceRate": 0.04,
    "enrollment": 17246,
    "graduationRate": 0.95,
    "medianEarnings6yr": 95400,
    "medianDebt": 11800,
    "website": "https://www.stanford.edu",
    "usnewsUrl": "https://www.usnews.com/best-colleges/stanford-1305",
    "nicheGrades": {
      "overall": "A+",
      "academics": "A+",
      "value": "A+",
      "diversity": "A",
      "campus": "A+",
      "athletics": "A+",
      "partyScene": "B+",
      "professors": "A+",
      "location": "A+",
      "dorms": "A-",
      "campusFood": "A-",
      "studentLife": "A+",
      "safety": "A"
    },
    "nicheUrl": "https://www.niche.com/colleges/stanford-university/"
  },
  {
    "name": "Carnegie Mellon University",
    "slug": "carnegie-mellon",
    "state": "PA",
    "city": "Pittsburgh",
    "region": "Mid-Atlantic",
    "csRanking": 1,
    "tuitionInState": 58924,
    "tuitionOutOfState": 58924,
    "roomAndBoard": 16796,
    "acceptanceRate": 0.11,
    "enrollment": 15818,
    "graduationRate": 0.91,
    "medianEarnings6yr": 97200,
    "medianDebt": 18500,
    "website": "https://www.cmu.edu",
    "usnewsUrl": "https://www.usnews.com/best-colleges/carnegie-mellon-3242",
    "nicheGrades": {
      "overall": "A+",
      "academics": "A+",
      "value": "A",
      "diversity": "A",
      "campus": "A-",
      "athletics": "B",
      "partyScene": "B-",
      "professors": "A",
      "location": "A-",
      "dorms": "B+",
      "campusFood": "B+",
      "studentLife": "B+",
      "safety": "A"
    },
    "nicheUrl": "https://www.niche.com/colleges/carnegie-mellon-university/"
  },
  {
    "name": "University of California Berkeley",
    "slug": "uc-berkeley",
    "state": "CA",
    "city": "Berkeley",
    "region": "West",
    "csRanking": 8,
    "tuitionInState": 14312,
    "tuitionOutOfState": 44066,
    "roomAndBoard": 21040,
    "acceptanceRate": 0.14,
    "enrollment": 45057,
    "graduationRate": 0.93,
    "medianEarnings6yr": 85800,
    "medianDebt": 9500,
    "website": "https://www.berkeley.edu",
    "usnewsUrl": "https://www.usnews.com/best-colleges/uc-berkeley-1312",
    "nicheGrades": {
      "overall": "A+",
      "academics": "A+",
      "value": "A+",
      "diversity": "A+",
      "campus": "A",
      "athletics": "A",
      "partyScene": "A-",
      "professors": "A",
      "location": "A+",
      "dorms": "B",
      "campusFood": "B+",
      "studentLife": "A",
      "safety": "B+"
    },
    "nicheUrl": "https://www.niche.com/colleges/university-of-california-berkeley/"
  },
  {
    "name": "University of Illinois Urbana-Champaign",
    "slug": "uiuc",
    "state": "IL",
    "city": "Champaign",
    "region": "Midwest",
    "csRanking": 2,
    "tuitionInState": 16862,
    "tuitionOutOfState": 34312,
    "roomAndBoard": 12424,
    "acceptanceRate": 0.45,
    "enrollment": 56303,
    "graduationRate": 0.85,
    "medianEarnings6yr": 80700,
    "medianDebt": 14000,
    "website": "https://illinois.edu",
    "usnewsUrl": "https://www.usnews.com/best-colleges/university-of-illinois-1775",
    "nicheGrades": {
      "overall": "A+",
      "academics": "A+",
      "value": "A+",
      "diversity": "A",
      "campus": "A",
      "athletics": "A",
      "partyScene": "A",
      "professors": "A",
      "location": "B+",
      "dorms": "B+",
      "campusFood": "B+",
      "studentLife": "A+",
      "safety": "B+"
    },
    "nicheUrl": "https://www.niche.com/colleges/university-of-illinois-urbana-champaign/"
  },
  {
    "name": "California Institute of Technology",
    "slug": "caltech",
    "state": "CA",
    "city": "Pasadena",
    "region": "West",
    "csRanking": 80,
    "tuitionInState": 60864,
    "tuitionOutOfState": 60864,
    "roomAndBoard": 19767,
    "acceptanceRate": 0.04,
    "enrollment": 2397,
    "graduationRate": 0.93,
    "medianEarnings6yr": 101700,
    "medianDebt": 15500,
    "website": "https://www.caltech.edu",
    "usnewsUrl": "https://www.usnews.com/best-colleges/caltech-1139",
    "nicheGrades": {
      "overall": "A+",
      "academics": "A+",
      "value": "A+",
      "diversity": "A",
      "campus": "B+",
      "athletics": "C+",
      "partyScene": "C",
      "professors": "A+",
      "location": "A+",
      "dorms": "A-",
      "campusFood": "A-",
      "studentLife": "B+",
      "safety": "A+"
    },
    "nicheUrl": "https://www.niche.com/colleges/california-institute-of-technology/"
  },
  {
    "name": "Georgia Institute of Technology",
    "slug": "georgia-tech",
    "state": "GA",
    "city": "Atlanta",
    "region": "Southeast",
    "csRanking": 4,
    "tuitionInState": 13040,
    "tuitionOutOfState": 31370,
    "roomAndBoard": 13066,
    "acceptanceRate": 0.17,
    "enrollment": 26806,
    "graduationRate": 0.87,
    "medianEarnings6yr": 83800,
    "medianDebt": 14000,
    "website": "https://www.gatech.edu",
    "usnewsUrl": "https://www.usnews.com/best-colleges/georgia-tech-1569",
    "nicheGrades": {
      "overall": "A+",
      "academics": "A+",
      "value": "A+",
      "diversity": "A",
      "campus": "A",
      "athletics": "A",
      "partyScene": "B+",
      "professors": "A",
      "location": "A",
      "dorms": "B+",
      "campusFood": "B+",
      "studentLife": "A",
      "safety": "B+"
    },
    "nicheUrl": "https://www.niche.com/colleges/georgia-institute-of-technology/"
  },
  {
    "name": "Cornell University",
    "slug": "cornell",
    "state": "NY",
    "city": "Ithaca",
    "region": "Northeast",
    "csRanking": 9,
    "tuitionInState": 61015,
    "tuitionOutOfState": 61015,
    "roomAndBoard": 17702,
    "acceptanceRate": 0.1,
    "enrollment": 25168,
    "graduationRate": 0.95,
    "medianEarnings6yr": 87600,
    "medianDebt": 16000,
    "website": "https://www.cornell.edu",
    "usnewsUrl": "https://www.usnews.com/best-colleges/cornell-2711",
    "nicheGrades": {
      "overall": "A+",
      "academics": "A+",
      "value": "A",
      "diversity": "A",
      "campus": "A",
      "athletics": "A",
      "partyScene": "A-",
      "professors": "A+",
      "location": "B+",
      "dorms": "A-",
      "campusFood": "A-",
      "studentLife": "A",
      "safety": "A"
    },
    "nicheUrl": "https://www.niche.com/colleges/cornell-university/"
  },
  {
    "name": "University of Washington",
    "slug": "uw",
    "state": "WA",
    "city": "Seattle",
    "region": "West",
    "csRanking": 7,
    "tuitionInState": 11839,
    "tuitionOutOfState": 38166,
    "roomAndBoard": 14889,
    "acceptanceRate": 0.52,
    "enrollment": 53600,
    "graduationRate": 0.84,
    "medianEarnings6yr": 80400,
    "medianDebt": 11000,
    "website": "https://www.washington.edu",
    "usnewsUrl": "https://www.usnews.com/best-colleges/university-of-washington-3798",
    "nicheGrades": {
      "overall": "A+",
      "academics": "A+",
      "value": "A+",
      "diversity": "A+",
      "campus": "A",
      "athletics": "A",
      "partyScene": "B+",
      "professors": "A",
      "location": "A+",
      "dorms": "B+",
      "campusFood": "B+",
      "studentLife": "A",
      "safety": "B+"
    },
    "nicheUrl": "https://www.niche.com/colleges/university-of-washington/"
  },
  {
    "name": "Princeton University",
    "slug": "princeton",
    "state": "NJ",
    "city": "Princeton",
    "region": "Mid-Atlantic",
    "csRanking": 17,
    "tuitionInState": 57410,
    "tuitionOutOfState": 57410,
    "roomAndBoard": 18180,
    "acceptanceRate": 0.04,
    "enrollment": 9018,
    "graduationRate": 0.97,
    "medianEarnings6yr": 90700,
    "medianDebt": 10000,
    "website": "https://www.princeton.edu",
    "usnewsUrl": "https://www.usnews.com/best-colleges/princeton-2627",
    "nicheGrades": {
      "overall": "A+",
      "academics": "A+",
      "value": "A+",
      "diversity": "A",
      "campus": "A+",
      "athletics": "A",
      "partyScene": "B+",
      "professors": "A+",
      "location": "A",
      "dorms": "A",
      "campusFood": "A",
      "studentLife": "A+",
      "safety": "A+"
    },
    "nicheUrl": "https://www.niche.com/colleges/princeton-university/"
  },
  {
    "name": "University of Texas at Austin",
    "slug": "ut-austin",
    "state": "TX",
    "city": "Austin",
    "region": "Southwest",
    "csRanking": 14,
    "tuitionInState": 11698,
    "tuitionOutOfState": 38228,
    "roomAndBoard": 12618,
    "acceptanceRate": 0.31,
    "enrollment": 51525,
    "graduationRate": 0.83,
    "medianEarnings6yr": 72700,
    "medianDebt": 12500,
    "website": "https://www.utexas.edu",
    "usnewsUrl": "https://www.usnews.com/best-colleges/ut-austin-3658",
    "nicheGrades": {
      "overall": "A+",
      "academics": "A+",
      "value": "A+",
      "diversity": "A",
      "campus": "A+",
      "athletics": "A+",
      "partyScene": "A",
      "professors": "A",
      "location": "A+",
      "dorms": "B",
      "campusFood": "B+",
      "studentLife": "A+",
      "safety": "B+"
    },
    "nicheUrl": "https://www.niche.com/colleges/university-of-texas-at-austin/"
  },
  {
    "name": "University of California Los Angeles",
    "slug": "ucla",
    "state": "CA",
    "city": "Los Angeles",
    "region": "West",
    "csRanking": 20,
    "tuitionInState": 13804,
    "tuitionOutOfState": 43473,
    "roomAndBoard": 20004,
    "acceptanceRate": 0.09,
    "enrollment": 47005,
    "graduationRate": 0.92,
    "medianEarnings6yr": 76700,
    "medianDebt": 11000,
    "website": "https://www.ucla.edu",
    "usnewsUrl": "https://www.usnews.com/best-colleges/ucla-1315",
    "nicheGrades": {
      "overall": "A+",
      "academics": "A+",
      "value": "A+",
      "diversity": "A+",
      "campus": "A",
      "athletics": "A+",
      "partyScene": "A",
      "professors": "A",
      "location": "A+",
      "dorms": "B",
      "campusFood": "B",
      "studentLife": "A+",
      "safety": "B+"
    },
    "nicheUrl": "https://www.niche.com/colleges/university-of-california-los-angeles/"
  },
  {
    "name": "University of Michigan",
    "slug": "michigan",
    "state": "MI",
    "city": "Ann Arbor",
    "region": "Midwest",
    "csRanking": 6,
    "tuitionInState": 16736,
    "tuitionOutOfState": 53470,
    "roomAndBoard": 13200,
    "acceptanceRate": 0.17,
    "enrollment": 48090,
    "graduationRate": 0.93,
    "medianEarnings6yr": 78500,
    "medianDebt": 13500,
    "website": "https://www.umich.edu",
    "usnewsUrl": "https://www.usnews.com/best-colleges/university-of-michigan-2325",
    "nicheGrades": {
      "overall": "A+",
      "academics": "A+",
      "value": "A+",
      "diversity": "A",
      "campus": "A+",
      "athletics": "A+",
      "partyScene": "A",
      "professors": "A+",
      "location": "A",
      "dorms": "A-",
      "campusFood": "A-",
      "studentLife": "A+",
      "safety": "A"
    },
    "nicheUrl": "https://www.niche.com/colleges/university-of-michigan/"
  },
  {
    "name": "Columbia University",
    "slug": "columbia",
    "state": "NY",
    "city": "New York",
    "region": "Northeast",
    "csRanking": 19,
    "tuitionInState": 63530,
    "tuitionOutOfState": 63530,
    "roomAndBoard": 16248,
    "acceptanceRate": 0.04,
    "enrollment": 32429,
    "graduationRate": 0.96,
    "medianEarnings6yr": 89600,
    "medianDebt": 19000,
    "website": "https://www.columbia.edu",
    "usnewsUrl": "https://www.usnews.com/best-colleges/columbia-2707",
    "nicheGrades": {
      "overall": "A+",
      "academics": "A+",
      "value": "B+",
      "diversity": "A+",
      "campus": "A-",
      "athletics": "B",
      "partyScene": "B+",
      "professors": "A+",
      "location": "A+",
      "dorms": "A-",
      "campusFood": "B+",
      "studentLife": "A",
      "safety": "B+"
    },
    "nicheUrl": "https://www.niche.com/colleges/columbia-university/"
  },
  {
    "name": "Harvard University",
    "slug": "harvard",
    "state": "MA",
    "city": "Cambridge",
    "region": "Northeast",
    "csRanking": 39,
    "tuitionInState": 57261,
    "tuitionOutOfState": 57261,
    "roomAndBoard": 20793,
    "acceptanceRate": 0.03,
    "enrollment": 23731,
    "graduationRate": 0.98,
    "medianEarnings6yr": 95700,
    "medianDebt": 12000,
    "website": "https://www.harvard.edu",
    "usnewsUrl": "https://www.usnews.com/best-colleges/harvard-2155",
    "nicheGrades": {
      "overall": "A+",
      "academics": "A+",
      "value": "A+",
      "diversity": "A+",
      "campus": "A",
      "athletics": "A",
      "partyScene": "B",
      "professors": "A+",
      "location": "A+",
      "dorms": "A+",
      "campusFood": "A-",
      "studentLife": "A",
      "safety": "A+"
    },
    "nicheUrl": "https://www.niche.com/colleges/harvard-university/"
  },
  {
    "name": "University of California San Diego",
    "slug": "ucsd",
    "state": "CA",
    "city": "La Jolla",
    "region": "West",
    "csRanking": 3,
    "tuitionInState": 14622,
    "tuitionOutOfState": 44574,
    "roomAndBoard": 18081,
    "acceptanceRate": 0.24,
    "enrollment": 42006,
    "graduationRate": 0.87,
    "medianEarnings6yr": 76200,
    "medianDebt": 10000,
    "website": "https://www.ucsd.edu",
    "usnewsUrl": "https://www.usnews.com/best-colleges/ucsd-1317",
    "nicheGrades": {
      "overall": "A+",
      "academics": "A+",
      "value": "A+",
      "diversity": "A+",
      "campus": "A",
      "athletics": "B",
      "partyScene": "B",
      "professors": "A",
      "location": "A+",
      "dorms": "A-",
      "campusFood": "B+",
      "studentLife": "A",
      "safety": "A"
    },
    "nicheUrl": "https://www.niche.com/colleges/university-of-california-san-diego/"
  },
  {
    "name": "University of Wisconsin-Madison",
    "slug": "uw-madison",
    "state": "WI",
    "city": "Madison",
    "region": "Midwest",
    "csRanking": 16,
    "tuitionInState": 11205,
    "tuitionOutOfState": 37785,
    "roomAndBoard": 12070,
    "acceptanceRate": 0.49,
    "enrollment": 49695,
    "graduationRate": 0.88,
    "medianEarnings6yr": 66700,
    "medianDebt": 12000,
    "website": "https://www.wisc.edu",
    "usnewsUrl": "https://www.usnews.com/best-colleges/uw-madison-3895",
    "nicheGrades": {
      "overall": "A+",
      "academics": "A+",
      "value": "A+",
      "diversity": "A-",
      "campus": "A+",
      "athletics": "A+",
      "partyScene": "A",
      "professors": "A",
      "location": "A",
      "dorms": "B+",
      "campusFood": "A-",
      "studentLife": "A+",
      "safety": "B+"
    },
    "nicheUrl": "https://www.niche.com/colleges/university-of-wisconsin---madison/"
  },
  {
    "name": "University of Maryland",
    "slug": "umd",
    "state": "MD",
    "city": "College Park",
    "region": "Mid-Atlantic",
    "csRanking": 9,
    "tuitionInState": 10595,
    "tuitionOutOfState": 36891,
    "roomAndBoard": 12510,
    "acceptanceRate": 0.44,
    "enrollment": 41200,
    "graduationRate": 0.87,
    "medianEarnings6yr": 72500,
    "medianDebt": 13000,
    "website": "https://www.umd.edu",
    "usnewsUrl": "https://www.usnews.com/best-colleges/university-of-maryland-2103",
    "nicheGrades": {
      "overall": "A+",
      "academics": "A+",
      "value": "A+",
      "diversity": "A",
      "campus": "A",
      "athletics": "A",
      "partyScene": "A-",
      "professors": "A",
      "location": "A",
      "dorms": "B+",
      "campusFood": "B+",
      "studentLife": "A",
      "safety": "B+"
    },
    "nicheUrl": "https://www.niche.com/colleges/university-of-maryland/"
  },
  {
    "name": "Purdue University",
    "slug": "purdue",
    "state": "IN",
    "city": "West Lafayette",
    "region": "Midwest",
    "csRanking": 13,
    "tuitionInState": 9992,
    "tuitionOutOfState": 28794,
    "roomAndBoard": 10030,
    "acceptanceRate": 0.53,
    "enrollment": 50539,
    "graduationRate": 0.83,
    "medianEarnings6yr": 72800,
    "medianDebt": 14000,
    "website": "https://www.purdue.edu",
    "usnewsUrl": "https://www.usnews.com/best-colleges/purdue-1825",
    "nicheGrades": {
      "overall": "A+",
      "academics": "A+",
      "value": "A+",
      "diversity": "A-",
      "campus": "A",
      "athletics": "A",
      "partyScene": "B+",
      "professors": "A",
      "location": "B",
      "dorms": "B+",
      "campusFood": "B+",
      "studentLife": "A",
      "safety": "A"
    },
    "nicheUrl": "https://www.niche.com/colleges/purdue-university/"
  },
  {
    "name": "Duke University",
    "slug": "duke",
    "state": "NC",
    "city": "Durham",
    "region": "Southeast",
    "csRanking": 29,
    "tuitionInState": 60244,
    "tuitionOutOfState": 60244,
    "roomAndBoard": 18130,
    "acceptanceRate": 0.06,
    "enrollment": 17325,
    "graduationRate": 0.96,
    "medianEarnings6yr": 85100,
    "medianDebt": 13000,
    "website": "https://www.duke.edu",
    "usnewsUrl": "https://www.usnews.com/best-colleges/duke-2920",
    "nicheGrades": {
      "overall": "A+",
      "academics": "A+",
      "value": "A",
      "diversity": "A",
      "campus": "A+",
      "athletics": "A+",
      "partyScene": "A-",
      "professors": "A+",
      "location": "A",
      "dorms": "A",
      "campusFood": "A",
      "studentLife": "A+",
      "safety": "A"
    },
    "nicheUrl": "https://www.niche.com/colleges/duke-university/"
  },
  {
    "name": "Rice University",
    "slug": "rice",
    "state": "TX",
    "city": "Houston",
    "region": "Southwest",
    "csRanking": 46,
    "tuitionInState": 54960,
    "tuitionOutOfState": 54960,
    "roomAndBoard": 16200,
    "acceptanceRate": 0.09,
    "enrollment": 7656,
    "graduationRate": 0.94,
    "medianEarnings6yr": 80200,
    "medianDebt": 17000,
    "website": "https://www.rice.edu",
    "usnewsUrl": "https://www.usnews.com/best-colleges/rice-3604",
    "nicheGrades": {
      "overall": "A+",
      "academics": "A+",
      "value": "A+",
      "diversity": "A",
      "campus": "A+",
      "athletics": "A",
      "partyScene": "B+",
      "professors": "A+",
      "location": "A",
      "dorms": "A+",
      "campusFood": "A",
      "studentLife": "A+",
      "safety": "A"
    },
    "nicheUrl": "https://www.niche.com/colleges/rice-university/"
  },
  {
    "name": "Northwestern University",
    "slug": "northwestern",
    "state": "IL",
    "city": "Evanston",
    "region": "Midwest",
    "csRanking": 25,
    "tuitionInState": 62391,
    "tuitionOutOfState": 62391,
    "roomAndBoard": 19449,
    "acceptanceRate": 0.07,
    "enrollment": 22157,
    "graduationRate": 0.97,
    "medianEarnings6yr": 85300,
    "medianDebt": 15000,
    "website": "https://www.northwestern.edu",
    "usnewsUrl": "https://www.usnews.com/best-colleges/northwestern-1739",
    "nicheGrades": {
      "overall": "A+",
      "academics": "A+",
      "value": "A",
      "diversity": "A",
      "campus": "A+",
      "athletics": "A",
      "partyScene": "B+",
      "professors": "A+",
      "location": "A+",
      "dorms": "A-",
      "campusFood": "A-",
      "studentLife": "A+",
      "safety": "A"
    },
    "nicheUrl": "https://www.niche.com/colleges/northwestern-university/"
  },
  {
    "name": "University of Pennsylvania",
    "slug": "upenn",
    "state": "PA",
    "city": "Philadelphia",
    "region": "Mid-Atlantic",
    "csRanking": 18,
    "tuitionInState": 63452,
    "tuitionOutOfState": 63452,
    "roomAndBoard": 17506,
    "acceptanceRate": 0.07,
    "enrollment": 28855,
    "graduationRate": 0.97,
    "medianEarnings6yr": 91600,
    "medianDebt": 16000,
    "website": "https://www.upenn.edu",
    "usnewsUrl": "https://www.usnews.com/best-colleges/university-of-pennsylvania-3378",
    "nicheGrades": {
      "overall": "A+",
      "academics": "A+",
      "value": "B+",
      "diversity": "A",
      "campus": "A",
      "athletics": "A",
      "partyScene": "A",
      "professors": "A+",
      "location": "A+",
      "dorms": "A",
      "campusFood": "A-",
      "studentLife": "A+",
      "safety": "B+"
    },
    "nicheUrl": "https://www.niche.com/colleges/university-of-pennsylvania/"
  },
  {
    "name": "Yale University",
    "slug": "yale",
    "state": "CT",
    "city": "New Haven",
    "region": "Northeast",
    "csRanking": 39,
    "tuitionInState": 62890,
    "tuitionOutOfState": 62890,
    "roomAndBoard": 18775,
    "acceptanceRate": 0.05,
    "enrollment": 14609,
    "graduationRate": 0.98,
    "medianEarnings6yr": 85500,
    "medianDebt": 12500,
    "website": "https://www.yale.edu",
    "usnewsUrl": "https://www.usnews.com/best-colleges/yale-1426",
    "nicheGrades": {
      "overall": "A+",
      "academics": "A+",
      "value": "A",
      "diversity": "A+",
      "campus": "A+",
      "athletics": "A",
      "partyScene": "B",
      "professors": "A+",
      "location": "A-",
      "dorms": "A+",
      "campusFood": "A",
      "studentLife": "A+",
      "safety": "A"
    },
    "nicheUrl": "https://www.niche.com/colleges/yale-university/"
  },
  {
    "name": "Brown University",
    "slug": "brown",
    "state": "RI",
    "city": "Providence",
    "region": "Northeast",
    "csRanking": 52,
    "tuitionInState": 65146,
    "tuitionOutOfState": 65146,
    "roomAndBoard": 16976,
    "acceptanceRate": 0.05,
    "enrollment": 10696,
    "graduationRate": 0.97,
    "medianEarnings6yr": 76800,
    "medianDebt": 14000,
    "website": "https://www.brown.edu",
    "usnewsUrl": "https://www.usnews.com/best-colleges/brown-3401",
    "nicheGrades": {
      "overall": "A+",
      "academics": "A+",
      "value": "B+",
      "diversity": "A",
      "campus": "A+",
      "athletics": "B+",
      "partyScene": "A",
      "professors": "A+",
      "location": "A",
      "dorms": "A-",
      "campusFood": "A-",
      "studentLife": "A+",
      "safety": "A"
    },
    "nicheUrl": "https://www.niche.com/colleges/brown-university/"
  },
  {
    "name": "University of Southern California",
    "slug": "usc",
    "state": "CA",
    "city": "Los Angeles",
    "region": "West",
    "csRanking": 21,
    "tuitionInState": 64726,
    "tuitionOutOfState": 64726,
    "roomAndBoard": 18190,
    "acceptanceRate": 0.12,
    "enrollment": 49699,
    "graduationRate": 0.92,
    "medianEarnings6yr": 77300,
    "medianDebt": 21000,
    "website": "https://www.usc.edu",
    "usnewsUrl": "https://www.usnews.com/best-colleges/usc-1328",
    "nicheGrades": {
      "overall": "A+",
      "academics": "A+",
      "value": "B",
      "diversity": "A+",
      "campus": "A+",
      "athletics": "A+",
      "partyScene": "A",
      "professors": "A",
      "location": "A+",
      "dorms": "A-",
      "campusFood": "A-",
      "studentLife": "A+",
      "safety": "B"
    },
    "nicheUrl": "https://www.niche.com/colleges/university-of-southern-california/"
  },
  {
    "name": "New York University",
    "slug": "nyu",
    "state": "NY",
    "city": "New York",
    "region": "Northeast",
    "csRanking": 14,
    "tuitionInState": 58168,
    "tuitionOutOfState": 58168,
    "roomAndBoard": 20472,
    "acceptanceRate": 0.12,
    "enrollment": 59144,
    "graduationRate": 0.87,
    "medianEarnings6yr": 71200,
    "medianDebt": 22000,
    "website": "https://www.nyu.edu",
    "usnewsUrl": "https://www.usnews.com/best-colleges/nyu-2785",
    "nicheGrades": {
      "overall": "A+",
      "academics": "A+",
      "value": "B",
      "diversity": "A+",
      "campus": "B+",
      "athletics": "C+",
      "partyScene": "A",
      "professors": "A",
      "location": "A+",
      "dorms": "B",
      "campusFood": "B",
      "studentLife": "A+",
      "safety": "B+"
    },
    "nicheUrl": "https://www.niche.com/colleges/new-york-university/"
  },
  {
    "name": "Virginia Tech",
    "slug": "virginia-tech",
    "state": "VA",
    "city": "Blacksburg",
    "region": "Southeast",
    "csRanking": 39,
    "tuitionInState": 13468,
    "tuitionOutOfState": 31908,
    "roomAndBoard": 10526,
    "acceptanceRate": 0.57,
    "enrollment": 37850,
    "graduationRate": 0.83,
    "medianEarnings6yr": 70200,
    "medianDebt": 15000,
    "website": "https://www.vt.edu",
    "usnewsUrl": "https://www.usnews.com/best-colleges/virginia-tech-3754",
    "nicheGrades": {
      "overall": "A+",
      "academics": "A+",
      "value": "A+",
      "diversity": "A-",
      "campus": "A",
      "athletics": "A",
      "partyScene": "A",
      "professors": "A",
      "location": "B+",
      "dorms": "B+",
      "campusFood": "B+",
      "studentLife": "A+",
      "safety": "A"
    },
    "nicheUrl": "https://www.niche.com/colleges/virginia-tech/"
  },
  {
    "name": "NC State University",
    "slug": "nc-state",
    "state": "NC",
    "city": "Raleigh",
    "region": "Southeast",
    "csRanking": 37,
    "tuitionInState": 9101,
    "tuitionOutOfState": 28444,
    "roomAndBoard": 11554,
    "acceptanceRate": 0.44,
    "enrollment": 38247,
    "graduationRate": 0.81,
    "medianEarnings6yr": 69800,
    "medianDebt": 16500,
    "website": "https://www.ncsu.edu",
    "usnewsUrl": "https://www.usnews.com/best-colleges/nc-state-2972",
    "nicheGrades": {
      "overall": "A+",
      "academics": "A+",
      "value": "A+",
      "diversity": "A-",
      "campus": "A",
      "athletics": "A",
      "partyScene": "B+",
      "professors": "A",
      "location": "A",
      "dorms": "B+",
      "campusFood": "B+",
      "studentLife": "A",
      "safety": "A"
    },
    "nicheUrl": "https://www.niche.com/colleges/north-carolina-state-university/"
  },
  {
    "name": "Ohio State University",
    "slug": "ohio-state",
    "state": "OH",
    "city": "Columbus",
    "region": "Midwest",
    "csRanking": 47,
    "tuitionInState": 11898,
    "tuitionOutOfState": 33520,
    "roomAndBoard": 12490,
    "acceptanceRate": 0.53,
    "enrollment": 66444,
    "graduationRate": 0.83,
    "medianEarnings6yr": 68500,
    "medianDebt": 13000,
    "website": "https://www.osu.edu",
    "usnewsUrl": "https://www.usnews.com/best-colleges/ohio-state-6883",
    "nicheGrades": {
      "overall": "A+",
      "academics": "A+",
      "value": "A+",
      "diversity": "A",
      "campus": "A+",
      "athletics": "A+",
      "partyScene": "A",
      "professors": "A",
      "location": "A",
      "dorms": "B+",
      "campusFood": "B+",
      "studentLife": "A+",
      "safety": "B+"
    },
    "nicheUrl": "https://www.niche.com/colleges/ohio-state-university/"
  },
  {
    "name": "Penn State University",
    "slug": "penn-state",
    "state": "PA",
    "city": "State College",
    "region": "Mid-Atlantic",
    "csRanking": 32,
    "tuitionInState": 18450,
    "tuitionOutOfState": 36820,
    "roomAndBoard": 12000,
    "acceptanceRate": 0.55,
    "enrollment": 89981,
    "graduationRate": 0.8,
    "medianEarnings6yr": 67500,
    "medianDebt": 15000,
    "website": "https://www.psu.edu",
    "usnewsUrl": "https://www.usnews.com/best-colleges/penn-state-3329",
    "nicheGrades": {
      "overall": "A+",
      "academics": "A",
      "value": "A",
      "diversity": "A-",
      "campus": "A+",
      "athletics": "A+",
      "partyScene": "A",
      "professors": "A",
      "location": "B",
      "dorms": "B+",
      "campusFood": "B+",
      "studentLife": "A+",
      "safety": "A"
    },
    "nicheUrl": "https://www.niche.com/colleges/pennsylvania-state-university/"
  },
  {
    "name": "University of Massachusetts Amherst",
    "slug": "umass",
    "state": "MA",
    "city": "Amherst",
    "region": "Northeast",
    "csRanking": 22,
    "tuitionInState": 16186,
    "tuitionOutOfState": 36161,
    "roomAndBoard": 14700,
    "acceptanceRate": 0.64,
    "enrollment": 32019,
    "graduationRate": 0.84,
    "medianEarnings6yr": 66500,
    "medianDebt": 14500,
    "website": "https://www.umass.edu",
    "usnewsUrl": "https://www.usnews.com/best-colleges/umass-2249",
    "nicheGrades": {
      "overall": "A",
      "academics": "A",
      "value": "A+",
      "diversity": "A",
      "campus": "A",
      "athletics": "A",
      "partyScene": "A",
      "professors": "A",
      "location": "B+",
      "dorms": "B+",
      "campusFood": "B+",
      "studentLife": "A",
      "safety": "B+"
    },
    "nicheUrl": "https://www.niche.com/colleges/university-of-massachusetts-amherst/"
  },
  {
    "name": "Rutgers University",
    "slug": "rutgers",
    "state": "NJ",
    "city": "New Brunswick",
    "region": "Mid-Atlantic",
    "csRanking": 29,
    "tuitionInState": 15307,
    "tuitionOutOfState": 31282,
    "roomAndBoard": 13998,
    "acceptanceRate": 0.61,
    "enrollment": 51043,
    "graduationRate": 0.82,
    "medianEarnings6yr": 68000,
    "medianDebt": 15000,
    "website": "https://www.rutgers.edu",
    "usnewsUrl": "https://www.usnews.com/best-colleges/rutgers-2629",
    "nicheGrades": {
      "overall": "A",
      "academics": "A",
      "value": "A+",
      "diversity": "A+",
      "campus": "B+",
      "athletics": "A",
      "partyScene": "A-",
      "professors": "A-",
      "location": "A-",
      "dorms": "B",
      "campusFood": "B",
      "studentLife": "A-",
      "safety": "B+"
    },
    "nicheUrl": "https://www.niche.com/colleges/rutgers-university/"
  },
  {
    "name": "NJIT",
    "slug": "njit",
    "state": "NJ",
    "city": "Newark",
    "region": "Mid-Atlantic",
    "csRanking": 63,
    "tuitionInState": 18250,
    "tuitionOutOfState": 33930,
    "roomAndBoard": 14200,
    "acceptanceRate": 0.67,
    "enrollment": 12100,
    "graduationRate": 0.66,
    "medianEarnings6yr": 72500,
    "medianDebt": 14000,
    "website": "https://www.njit.edu",
    "usnewsUrl": "https://www.usnews.com/best-colleges/njit-2621",
    "nicheGrades": {
      "overall": "B+",
      "academics": "A",
      "value": "A",
      "diversity": "A",
      "campus": "B",
      "athletics": "C",
      "partyScene": "C",
      "professors": "B+",
      "location": "B+",
      "dorms": "B",
      "campusFood": "B-",
      "studentLife": "B",
      "safety": "B"
    },
    "nicheUrl": "https://www.niche.com/colleges/new-jersey-institute-of-technology/"
  },
  {
    "name": "Rensselaer Polytechnic Institute",
    "slug": "rpi",
    "state": "NY",
    "city": "Troy",
    "region": "Northeast",
    "csRanking": 89,
    "tuitionInState": 60990,
    "tuitionOutOfState": 60990,
    "roomAndBoard": 17000,
    "acceptanceRate": 0.61,
    "enrollment": 10400,
    "graduationRate": 0.84,
    "medianEarnings6yr": 78200,
    "medianDebt": 21000,
    "website": "https://www.rpi.edu",
    "usnewsUrl": "https://www.usnews.com/best-colleges/rpi-2803",
    "nicheGrades": {
      "overall": "A",
      "academics": "A+",
      "value": "B",
      "diversity": "A-",
      "campus": "B+",
      "athletics": "B",
      "partyScene": "C+",
      "professors": "A",
      "location": "B",
      "dorms": "B+",
      "campusFood": "B",
      "studentLife": "B+",
      "safety": "A-"
    },
    "nicheUrl": "https://www.niche.com/colleges/rensselaer-polytechnic-institute/"
  },
  {
    "name": "Stony Brook University",
    "slug": "stony-brook",
    "state": "NY",
    "city": "Stony Brook",
    "region": "Northeast",
    "csRanking": 25,
    "tuitionInState": 10168,
    "tuitionOutOfState": 28048,
    "roomAndBoard": 15600,
    "acceptanceRate": 0.49,
    "enrollment": 26955,
    "graduationRate": 0.76,
    "medianEarnings6yr": 65200,
    "medianDebt": 13000,
    "website": "https://www.stonybrook.edu",
    "usnewsUrl": "https://www.usnews.com/best-colleges/stony-brook-2838",
    "nicheGrades": {
      "overall": "A",
      "academics": "A+",
      "value": "A+",
      "diversity": "A+",
      "campus": "B+",
      "athletics": "B",
      "partyScene": "C",
      "professors": "A",
      "location": "B+",
      "dorms": "B-",
      "campusFood": "B-",
      "studentLife": "B",
      "safety": "A"
    },
    "nicheUrl": "https://www.niche.com/colleges/stony-brook-university/"
  },
  {
    "name": "Boston University",
    "slug": "boston-u",
    "state": "MA",
    "city": "Boston",
    "region": "Northeast",
    "csRanking": 33,
    "tuitionInState": 60050,
    "tuitionOutOfState": 60050,
    "roomAndBoard": 17530,
    "acceptanceRate": 0.18,
    "enrollment": 36714,
    "graduationRate": 0.88,
    "medianEarnings6yr": 72800,
    "medianDebt": 18500,
    "website": "https://www.bu.edu",
    "usnewsUrl": "https://www.usnews.com/best-colleges/bu-2130",
    "nicheGrades": {
      "overall": "A+",
      "academics": "A+",
      "value": "B",
      "diversity": "A+",
      "campus": "A",
      "athletics": "A",
      "partyScene": "A",
      "professors": "A",
      "location": "A+",
      "dorms": "A-",
      "campusFood": "A-",
      "studentLife": "A+",
      "safety": "A"
    },
    "nicheUrl": "https://www.niche.com/colleges/boston-university/"
  },
  {
    "name": "Northeastern University",
    "slug": "northeastern",
    "state": "MA",
    "city": "Boston",
    "region": "Northeast",
    "csRanking": 12,
    "tuitionInState": 59600,
    "tuitionOutOfState": 59600,
    "roomAndBoard": 18290,
    "acceptanceRate": 0.18,
    "enrollment": 22125,
    "graduationRate": 0.88,
    "medianEarnings6yr": 81200,
    "medianDebt": 17000,
    "website": "https://www.northeastern.edu",
    "usnewsUrl": "https://www.usnews.com/best-colleges/northeastern-2199",
    "nicheGrades": {
      "overall": "A+",
      "academics": "A+",
      "value": "B+",
      "diversity": "A+",
      "campus": "A",
      "athletics": "B",
      "partyScene": "A",
      "professors": "A",
      "location": "A+",
      "dorms": "A-",
      "campusFood": "A-",
      "studentLife": "A+",
      "safety": "A"
    },
    "nicheUrl": "https://www.niche.com/colleges/northeastern-university/"
  },
  {
    "name": "University of Minnesota",
    "slug": "umn",
    "state": "MN",
    "city": "Minneapolis",
    "region": "Midwest",
    "csRanking": 47,
    "tuitionInState": 15437,
    "tuitionOutOfState": 31680,
    "roomAndBoard": 10900,
    "acceptanceRate": 0.57,
    "enrollment": 54955,
    "graduationRate": 0.82,
    "medianEarnings6yr": 67500,
    "medianDebt": 14500,
    "website": "https://www.umn.edu",
    "usnewsUrl": "https://www.usnews.com/best-colleges/university-of-minnesota-2389",
    "nicheGrades": {
      "overall": "A",
      "academics": "A",
      "value": "A+",
      "diversity": "A",
      "campus": "A",
      "athletics": "A",
      "partyScene": "B+",
      "professors": "A",
      "location": "A",
      "dorms": "B+",
      "campusFood": "B+",
      "studentLife": "A",
      "safety": "B+"
    },
    "nicheUrl": "https://www.niche.com/colleges/university-of-minnesota/"
  },
  {
    "name": "Iowa State University",
    "slug": "iowa-state",
    "state": "IA",
    "city": "Ames",
    "region": "Midwest",
    "csRanking": 80,
    "tuitionInState": 9540,
    "tuitionOutOfState": 26590,
    "roomAndBoard": 9510,
    "acceptanceRate": 0.88,
    "enrollment": 30671,
    "graduationRate": 0.73,
    "medianEarnings6yr": 61200,
    "medianDebt": 13000,
    "website": "https://www.iastate.edu",
    "usnewsUrl": "https://www.usnews.com/best-colleges/iowa-state-1869",
    "nicheGrades": {
      "overall": "A",
      "academics": "A",
      "value": "A+",
      "diversity": "B+",
      "campus": "A",
      "athletics": "A",
      "partyScene": "A-",
      "professors": "A",
      "location": "B",
      "dorms": "B+",
      "campusFood": "B+",
      "studentLife": "A",
      "safety": "A"
    },
    "nicheUrl": "https://www.niche.com/colleges/iowa-state-university/"
  },
  {
    "name": "Arizona State University",
    "slug": "asu",
    "state": "AZ",
    "city": "Tempe",
    "region": "Southwest",
    "csRanking": 42,
    "tuitionInState": 11948,
    "tuitionOutOfState": 27372,
    "roomAndBoard": 13064,
    "acceptanceRate": 0.88,
    "enrollment": 77881,
    "graduationRate": 0.67,
    "medianEarnings6yr": 60200,
    "medianDebt": 15000,
    "website": "https://www.asu.edu",
    "usnewsUrl": "https://www.usnews.com/best-colleges/asu-1081",
    "nicheGrades": {
      "overall": "A",
      "academics": "A",
      "value": "A+",
      "diversity": "A",
      "campus": "A",
      "athletics": "A",
      "partyScene": "A",
      "professors": "A-",
      "location": "A",
      "dorms": "B",
      "campusFood": "B+",
      "studentLife": "A",
      "safety": "B+"
    },
    "nicheUrl": "https://www.niche.com/colleges/arizona-state-university/"
  },
  {
    "name": "University of Texas at Dallas",
    "slug": "ut-dallas",
    "state": "TX",
    "city": "Richardson",
    "region": "Southwest",
    "csRanking": 55,
    "tuitionInState": 13878,
    "tuitionOutOfState": 32952,
    "roomAndBoard": 10800,
    "acceptanceRate": 0.82,
    "enrollment": 29786,
    "graduationRate": 0.73,
    "medianEarnings6yr": 70500,
    "medianDebt": 14000,
    "website": "https://www.utdallas.edu",
    "usnewsUrl": "https://www.usnews.com/best-colleges/ut-dallas-227526",
    "nicheGrades": {
      "overall": "A",
      "academics": "A+",
      "value": "A+",
      "diversity": "A+",
      "campus": "B+",
      "athletics": "C",
      "partyScene": "C",
      "professors": "A",
      "location": "B+",
      "dorms": "B",
      "campusFood": "B",
      "studentLife": "B+",
      "safety": "A"
    },
    "nicheUrl": "https://www.niche.com/colleges/the-university-of-texas-at-dallas/"
  },
  {
    "name": "University of Florida",
    "slug": "uf",
    "state": "FL",
    "city": "Gainesville",
    "region": "Southeast",
    "csRanking": 62,
    "tuitionInState": 6380,
    "tuitionOutOfState": 28658,
    "roomAndBoard": 10800,
    "acceptanceRate": 0.23,
    "enrollment": 57656,
    "graduationRate": 0.9,
    "medianEarnings6yr": 64800,
    "medianDebt": 11000,
    "website": "https://www.ufl.edu",
    "usnewsUrl": "https://www.usnews.com/best-colleges/university-of-florida-1535",
    "nicheGrades": {
      "overall": "A+",
      "academics": "A+",
      "value": "A+",
      "diversity": "A",
      "campus": "A+",
      "athletics": "A+",
      "partyScene": "A",
      "professors": "A",
      "location": "A",
      "dorms": "B+",
      "campusFood": "B+",
      "studentLife": "A+",
      "safety": "B+"
    },
    "nicheUrl": "https://www.niche.com/colleges/university-of-florida/"
  },
  {
    "name": "University of California Irvine",
    "slug": "uci",
    "state": "CA",
    "city": "Irvine",
    "region": "West",
    "csRanking": 24,
    "tuitionInState": 13727,
    "tuitionOutOfState": 43619,
    "roomAndBoard": 19800,
    "acceptanceRate": 0.27,
    "enrollment": 36908,
    "graduationRate": 0.85,
    "medianEarnings6yr": 72800,
    "medianDebt": 10000,
    "website": "https://www.uci.edu",
    "usnewsUrl": "https://www.usnews.com/best-colleges/uci-1314",
    "nicheGrades": {
      "overall": "A+",
      "academics": "A+",
      "value": "A+",
      "diversity": "A+",
      "campus": "A",
      "athletics": "B",
      "partyScene": "B",
      "professors": "A",
      "location": "A+",
      "dorms": "A-",
      "campusFood": "A-",
      "studentLife": "A",
      "safety": "A+"
    },
    "nicheUrl": "https://www.niche.com/colleges/university-of-california-irvine/"
  },
  {
    "name": "University of California Davis",
    "slug": "uc-davis",
    "state": "CA",
    "city": "Davis",
    "region": "West",
    "csRanking": 47,
    "tuitionInState": 14679,
    "tuitionOutOfState": 44627,
    "roomAndBoard": 19200,
    "acceptanceRate": 0.46,
    "enrollment": 40031,
    "graduationRate": 0.87,
    "medianEarnings6yr": 69500,
    "medianDebt": 10500,
    "website": "https://www.ucdavis.edu",
    "usnewsUrl": "https://www.usnews.com/best-colleges/uc-davis-1313",
    "nicheGrades": {
      "overall": "A+",
      "academics": "A+",
      "value": "A+",
      "diversity": "A+",
      "campus": "A",
      "athletics": "A",
      "partyScene": "B+",
      "professors": "A",
      "location": "A",
      "dorms": "B+",
      "campusFood": "B+",
      "studentLife": "A",
      "safety": "A"
    },
    "nicheUrl": "https://www.niche.com/colleges/university-of-california-davis/"
  },
  {
    "name": "University of California Santa Barbara",
    "slug": "ucsb",
    "state": "CA",
    "city": "Santa Barbara",
    "region": "West",
    "csRanking": 33,
    "tuitionInState": 14622,
    "tuitionOutOfState": 44574,
    "roomAndBoard": 19500,
    "acceptanceRate": 0.26,
    "enrollment": 26181,
    "graduationRate": 0.86,
    "medianEarnings6yr": 68900,
    "medianDebt": 10000,
    "website": "https://www.ucsb.edu",
    "usnewsUrl": "https://www.usnews.com/best-colleges/ucsb-1320",
    "nicheGrades": {
      "overall": "A+",
      "academics": "A+",
      "value": "A+",
      "diversity": "A",
      "campus": "A+",
      "athletics": "A",
      "partyScene": "A+",
      "professors": "A",
      "location": "A+",
      "dorms": "A-",
      "campusFood": "A-",
      "studentLife": "A+",
      "safety": "A"
    },
    "nicheUrl": "https://www.niche.com/colleges/university-of-california-santa-barbara/"
  },
  {
    "name": "University of California Santa Cruz",
    "slug": "ucsc",
    "state": "CA",
    "city": "Santa Cruz",
    "region": "West",
    "csRanking": 37,
    "tuitionInState": 14020,
    "tuitionOutOfState": 43972,
    "roomAndBoard": 20600,
    "acceptanceRate": 0.47,
    "enrollment": 19161,
    "graduationRate": 0.8,
    "medianEarnings6yr": 66200,
    "medianDebt": 11000,
    "website": "https://www.ucsc.edu",
    "usnewsUrl": "https://www.usnews.com/best-colleges/ucsc-1321",
    "nicheGrades": {
      "overall": "A",
      "academics": "A",
      "value": "A",
      "diversity": "A+",
      "campus": "A+",
      "athletics": "B",
      "partyScene": "A-",
      "professors": "A",
      "location": "A+",
      "dorms": "B+",
      "campusFood": "B",
      "studentLife": "A",
      "safety": "A"
    },
    "nicheUrl": "https://www.niche.com/colleges/university-of-california-santa-cruz/"
  },
  {
    "name": "Colorado School of Mines",
    "slug": "mines",
    "state": "CO",
    "city": "Golden",
    "region": "West",
    "csRanking": 107,
    "tuitionInState": 19650,
    "tuitionOutOfState": 40350,
    "roomAndBoard": 12450,
    "acceptanceRate": 0.57,
    "enrollment": 6800,
    "graduationRate": 0.78,
    "medianEarnings6yr": 76500,
    "medianDebt": 20000,
    "website": "https://www.mines.edu",
    "usnewsUrl": "https://www.usnews.com/best-colleges/colorado-school-of-mines-1348",
    "nicheGrades": {
      "overall": "A",
      "academics": "A+",
      "value": "A+",
      "diversity": "B+",
      "campus": "B+",
      "athletics": "B",
      "partyScene": "B",
      "professors": "A",
      "location": "A",
      "dorms": "B",
      "campusFood": "B",
      "studentLife": "B+",
      "safety": "A"
    },
    "nicheUrl": "https://www.niche.com/colleges/colorado-school-of-mines/"
  },
  {
    "name": "Clemson University",
    "slug": "clemson",
    "state": "SC",
    "city": "Clemson",
    "region": "Southeast",
    "csRanking": 75,
    "tuitionInState": 14896,
    "tuitionOutOfState": 36476,
    "roomAndBoard": 10300,
    "acceptanceRate": 0.44,
    "enrollment": 27669,
    "graduationRate": 0.82,
    "medianEarnings6yr": 67700,
    "medianDebt": 14500,
    "website": "https://www.clemson.edu",
    "usnewsUrl": "https://www.usnews.com/best-colleges/clemson-3425",
    "nicheGrades": {
      "overall": "A+",
      "academics": "A",
      "value": "A+",
      "diversity": "B+",
      "campus": "A+",
      "athletics": "A+",
      "partyScene": "A",
      "professors": "A",
      "location": "A",
      "dorms": "B+",
      "campusFood": "B+",
      "studentLife": "A+",
      "safety": "A"
    },
    "nicheUrl": "https://www.niche.com/colleges/clemson-university/"
  },
  {
    "name": "Michigan State University",
    "slug": "michigan-state",
    "state": "MI",
    "city": "East Lansing",
    "region": "Midwest",
    "csRanking": 67,
    "tuitionInState": 14460,
    "tuitionOutOfState": 39766,
    "roomAndBoard": 11100,
    "acceptanceRate": 0.76,
    "enrollment": 50019,
    "graduationRate": 0.8,
    "medianEarnings6yr": 62500,
    "medianDebt": 13500,
    "website": "https://www.msu.edu",
    "usnewsUrl": "https://www.usnews.com/best-colleges/michigan-state-2290",
    "nicheGrades": {
      "overall": "A+",
      "academics": "A",
      "value": "A+",
      "diversity": "A",
      "campus": "A",
      "athletics": "A+",
      "partyScene": "A",
      "professors": "A",
      "location": "A",
      "dorms": "B+",
      "campusFood": "B+",
      "studentLife": "A+",
      "safety": "B+"
    },
    "nicheUrl": "https://www.niche.com/colleges/michigan-state-university/"
  },
  {
    "name": "Indiana University Bloomington",
    "slug": "indiana",
    "state": "IN",
    "city": "Bloomington",
    "region": "Midwest",
    "csRanking": 55,
    "tuitionInState": 10948,
    "tuitionOutOfState": 36512,
    "roomAndBoard": 11318,
    "acceptanceRate": 0.8,
    "enrollment": 43710,
    "graduationRate": 0.8,
    "medianEarnings6yr": 61500,
    "medianDebt": 14000,
    "website": "https://www.indiana.edu",
    "usnewsUrl": "https://www.usnews.com/best-colleges/indiana-university-1809",
    "nicheGrades": {
      "overall": "A+",
      "academics": "A",
      "value": "A+",
      "diversity": "A",
      "campus": "A+",
      "athletics": "A",
      "partyScene": "A+",
      "professors": "A",
      "location": "A",
      "dorms": "B+",
      "campusFood": "B+",
      "studentLife": "A+",
      "safety": "B+"
    },
    "nicheUrl": "https://www.niche.com/colleges/indiana-university-bloomington/"
  },
  {
    "name": "University of Pittsburgh",
    "slug": "pitt",
    "state": "PA",
    "city": "Pittsburgh",
    "region": "Mid-Atlantic",
    "csRanking": 63,
    "tuitionInState": 19760,
    "tuitionOutOfState": 34310,
    "roomAndBoard": 12600,
    "acceptanceRate": 0.52,
    "enrollment": 33000,
    "graduationRate": 0.84,
    "medianEarnings6yr": 68500,
    "medianDebt": 15000,
    "website": "https://www.pitt.edu",
    "usnewsUrl": "https://www.usnews.com/best-colleges/university-of-pittsburgh-3379",
    "nicheGrades": {
      "overall": "A",
      "academics": "A",
      "value": "A",
      "diversity": "A",
      "campus": "A",
      "athletics": "A",
      "partyScene": "A",
      "professors": "A",
      "location": "A",
      "dorms": "B+",
      "campusFood": "B+",
      "studentLife": "A",
      "safety": "B+"
    },
    "nicheUrl": "https://www.niche.com/colleges/university-of-pittsburgh/"
  },
  {
    "name": "Syracuse University",
    "slug": "syracuse",
    "state": "NY",
    "city": "Syracuse",
    "region": "Northeast",
    "csRanking": 107,
    "tuitionInState": 58074,
    "tuitionOutOfState": 58074,
    "roomAndBoard": 17580,
    "acceptanceRate": 0.6,
    "enrollment": 22157,
    "graduationRate": 0.84,
    "medianEarnings6yr": 66200,
    "medianDebt": 20000,
    "website": "https://www.syracuse.edu",
    "usnewsUrl": "https://www.usnews.com/best-colleges/syracuse-2882",
    "nicheGrades": {
      "overall": "A",
      "academics": "A",
      "value": "B",
      "diversity": "A",
      "campus": "A+",
      "athletics": "A+",
      "partyScene": "A",
      "professors": "A",
      "location": "B",
      "dorms": "B+",
      "campusFood": "B+",
      "studentLife": "A+",
      "safety": "B+"
    },
    "nicheUrl": "https://www.niche.com/colleges/syracuse-university/"
  },
  {
    "name": "Drexel University",
    "slug": "drexel",
    "state": "PA",
    "city": "Philadelphia",
    "region": "Mid-Atlantic",
    "csRanking": 89,
    "tuitionInState": 58308,
    "tuitionOutOfState": 58308,
    "roomAndBoard": 16030,
    "acceptanceRate": 0.79,
    "enrollment": 24193,
    "graduationRate": 0.72,
    "medianEarnings6yr": 71000,
    "medianDebt": 22000,
    "website": "https://www.drexel.edu",
    "usnewsUrl": "https://www.usnews.com/best-colleges/drexel-3256",
    "nicheGrades": {
      "overall": "A",
      "academics": "A",
      "value": "B",
      "diversity": "A",
      "campus": "B+",
      "athletics": "B",
      "partyScene": "B+",
      "professors": "A",
      "location": "A+",
      "dorms": "B",
      "campusFood": "B",
      "studentLife": "A",
      "safety": "B+"
    },
    "nicheUrl": "https://www.niche.com/colleges/drexel-university/"
  },
  {
    "name": "Stevens Institute of Technology",
    "slug": "stevens",
    "state": "NJ",
    "city": "Hoboken",
    "region": "Mid-Atlantic",
    "csRanking": 70,
    "tuitionInState": 56792,
    "tuitionOutOfState": 56792,
    "roomAndBoard": 17800,
    "acceptanceRate": 0.46,
    "enrollment": 8050,
    "graduationRate": 0.81,
    "medianEarnings6yr": 82000,
    "medianDebt": 20000,
    "website": "https://www.stevens.edu",
    "usnewsUrl": "https://www.usnews.com/best-colleges/stevens-2639",
    "nicheGrades": {
      "overall": "A",
      "academics": "A+",
      "value": "B+",
      "diversity": "A",
      "campus": "A-",
      "athletics": "B",
      "partyScene": "B",
      "professors": "A",
      "location": "A+",
      "dorms": "B+",
      "campusFood": "B",
      "studentLife": "A-",
      "safety": "A"
    },
    "nicheUrl": "https://www.niche.com/colleges/stevens-institute-of-technology/"
  },
  {
    "name": "Worcester Polytechnic Institute",
    "slug": "wpi",
    "state": "MA",
    "city": "Worcester",
    "region": "Northeast",
    "csRanking": 75,
    "tuitionInState": 57834,
    "tuitionOutOfState": 57834,
    "roomAndBoard": 16200,
    "acceptanceRate": 0.56,
    "enrollment": 6600,
    "graduationRate": 0.85,
    "medianEarnings6yr": 80000,
    "medianDebt": 19000,
    "website": "https://www.wpi.edu",
    "usnewsUrl": "https://www.usnews.com/best-colleges/wpi-2233",
    "nicheGrades": {
      "overall": "A",
      "academics": "A+",
      "value": "B+",
      "diversity": "A-",
      "campus": "B+",
      "athletics": "B",
      "partyScene": "B",
      "professors": "A",
      "location": "B",
      "dorms": "B+",
      "campusFood": "B",
      "studentLife": "B+",
      "safety": "A"
    },
    "nicheUrl": "https://www.niche.com/colleges/worcester-polytechnic-institute/"
  },
  {
    "name": "Rochester Institute of Technology",
    "slug": "rit",
    "state": "NY",
    "city": "Rochester",
    "region": "Northeast",
    "csRanking": 57,
    "tuitionInState": 52380,
    "tuitionOutOfState": 52380,
    "roomAndBoard": 14670,
    "acceptanceRate": 0.67,
    "enrollment": 18400,
    "graduationRate": 0.71,
    "medianEarnings6yr": 72500,
    "medianDebt": 21000,
    "website": "https://www.rit.edu",
    "usnewsUrl": "https://www.usnews.com/best-colleges/rit-2806",
    "nicheGrades": {
      "overall": "A",
      "academics": "A",
      "value": "B+",
      "diversity": "A",
      "campus": "B+",
      "athletics": "B",
      "partyScene": "C",
      "professors": "A",
      "location": "B",
      "dorms": "B+",
      "campusFood": "B+",
      "studentLife": "B+",
      "safety": "A"
    },
    "nicheUrl": "https://www.niche.com/colleges/rochester-institute-of-technology/"
  },
  {
    "name": "George Mason University",
    "slug": "george-mason",
    "state": "VA",
    "city": "Fairfax",
    "region": "Mid-Atlantic",
    "csRanking": 33,
    "tuitionInState": 12372,
    "tuitionOutOfState": 34970,
    "roomAndBoard": 13000,
    "acceptanceRate": 0.86,
    "enrollment": 38000,
    "graduationRate": 0.73,
    "medianEarnings6yr": 68000,
    "medianDebt": 14000,
    "website": "https://www.gmu.edu",
    "usnewsUrl": "https://www.usnews.com/best-colleges/gmu-6928",
    "nicheGrades": {
      "overall": "A",
      "academics": "A",
      "value": "A+",
      "diversity": "A+",
      "campus": "B+",
      "athletics": "B",
      "partyScene": "B",
      "professors": "A",
      "location": "A",
      "dorms": "B",
      "campusFood": "B",
      "studentLife": "B+",
      "safety": "A"
    },
    "nicheUrl": "https://www.niche.com/colleges/george-mason-university/"
  },
  {
    "name": "University of Colorado Boulder",
    "slug": "cu-boulder",
    "state": "CO",
    "city": "Boulder",
    "region": "West",
    "csRanking": 47,
    "tuitionInState": 12086,
    "tuitionOutOfState": 36736,
    "roomAndBoard": 14200,
    "acceptanceRate": 0.78,
    "enrollment": 38547,
    "graduationRate": 0.74,
    "medianEarnings6yr": 64500,
    "medianDebt": 14500,
    "website": "https://www.colorado.edu",
    "usnewsUrl": "https://www.usnews.com/best-colleges/cu-boulder-1370",
    "nicheGrades": {
      "overall": "A+",
      "academics": "A",
      "value": "A+",
      "diversity": "A-",
      "campus": "A+",
      "athletics": "A",
      "partyScene": "A+",
      "professors": "A",
      "location": "A+",
      "dorms": "B+",
      "campusFood": "B+",
      "studentLife": "A+",
      "safety": "B+"
    },
    "nicheUrl": "https://www.niche.com/colleges/university-of-colorado-boulder/"
  },
  {
    "name": "Oregon State University",
    "slug": "oregon-state",
    "state": "OR",
    "city": "Corvallis",
    "region": "West",
    "csRanking": 53,
    "tuitionInState": 12960,
    "tuitionOutOfState": 31455,
    "roomAndBoard": 12900,
    "acceptanceRate": 0.82,
    "enrollment": 34600,
    "graduationRate": 0.67,
    "medianEarnings6yr": 62000,
    "medianDebt": 15000,
    "website": "https://oregonstate.edu",
    "usnewsUrl": "https://www.usnews.com/best-colleges/oregon-state-3210",
    "nicheGrades": {
      "overall": "A",
      "academics": "A",
      "value": "A+",
      "diversity": "B+",
      "campus": "A",
      "athletics": "A",
      "partyScene": "B+",
      "professors": "A",
      "location": "A",
      "dorms": "B+",
      "campusFood": "B+",
      "studentLife": "A",
      "safety": "A"
    },
    "nicheUrl": "https://www.niche.com/colleges/oregon-state-university/"
  },
  {
    "name": "Washington State University",
    "slug": "wsu",
    "state": "WA",
    "city": "Pullman",
    "region": "West",
    "csRanking": 86,
    "tuitionInState": 11861,
    "tuitionOutOfState": 26391,
    "roomAndBoard": 11450,
    "acceptanceRate": 0.76,
    "enrollment": 31615,
    "graduationRate": 0.65,
    "medianEarnings6yr": 59500,
    "medianDebt": 15500,
    "website": "https://www.wsu.edu",
    "usnewsUrl": "https://www.usnews.com/best-colleges/wsu-3800",
    "nicheGrades": {
      "overall": "A",
      "academics": "A",
      "value": "A+",
      "diversity": "B+",
      "campus": "A",
      "athletics": "A",
      "partyScene": "A",
      "professors": "A",
      "location": "B",
      "dorms": "B+",
      "campusFood": "B+",
      "studentLife": "A",
      "safety": "A"
    },
    "nicheUrl": "https://www.niche.com/colleges/washington-state-university/"
  },
  {
    "name": "Florida State University",
    "slug": "fsu",
    "state": "FL",
    "city": "Tallahassee",
    "region": "Southeast",
    "csRanking": 67,
    "tuitionInState": 6517,
    "tuitionOutOfState": 21673,
    "roomAndBoard": 10600,
    "acceptanceRate": 0.25,
    "enrollment": 45610,
    "graduationRate": 0.82,
    "medianEarnings6yr": 58800,
    "medianDebt": 12000,
    "website": "https://www.fsu.edu",
    "usnewsUrl": "https://www.usnews.com/best-colleges/florida-state-1519",
    "nicheGrades": {
      "overall": "A+",
      "academics": "A",
      "value": "A+",
      "diversity": "A",
      "campus": "A+",
      "athletics": "A+",
      "partyScene": "A+",
      "professors": "A",
      "location": "A",
      "dorms": "B+",
      "campusFood": "B+",
      "studentLife": "A+",
      "safety": "B+"
    },
    "nicheUrl": "https://www.niche.com/colleges/florida-state-university/"
  },
  {
    "name": "University of Arizona",
    "slug": "u-arizona",
    "state": "AZ",
    "city": "Tucson",
    "region": "Southwest",
    "csRanking": 83,
    "tuitionInState": 12746,
    "tuitionOutOfState": 34794,
    "roomAndBoard": 12200,
    "acceptanceRate": 0.85,
    "enrollment": 49403,
    "graduationRate": 0.67,
    "medianEarnings6yr": 59200,
    "medianDebt": 14500,
    "website": "https://www.arizona.edu",
    "usnewsUrl": "https://www.usnews.com/best-colleges/university-of-arizona-1083",
    "nicheGrades": {
      "overall": "A",
      "academics": "A",
      "value": "A+",
      "diversity": "A",
      "campus": "A",
      "athletics": "A",
      "partyScene": "A",
      "professors": "A",
      "location": "A+",
      "dorms": "B+",
      "campusFood": "B+",
      "studentLife": "A",
      "safety": "B+"
    },
    "nicheUrl": "https://www.niche.com/colleges/university-of-arizona/"
  },
  {
    "name": "University of Utah",
    "slug": "utah",
    "state": "UT",
    "city": "Salt Lake City",
    "region": "West",
    "csRanking": 31,
    "tuitionInState": 9766,
    "tuitionOutOfState": 31007,
    "roomAndBoard": 11400,
    "acceptanceRate": 0.83,
    "enrollment": 34098,
    "graduationRate": 0.69,
    "medianEarnings6yr": 62500,
    "medianDebt": 14000,
    "website": "https://www.utah.edu",
    "usnewsUrl": "https://www.usnews.com/best-colleges/university-of-utah-3675",
    "nicheGrades": {
      "overall": "A",
      "academics": "A",
      "value": "A+",
      "diversity": "B+",
      "campus": "A",
      "athletics": "A",
      "partyScene": "B",
      "professors": "A",
      "location": "A+",
      "dorms": "B",
      "campusFood": "B",
      "studentLife": "A",
      "safety": "A"
    },
    "nicheUrl": "https://www.niche.com/colleges/university-of-utah/"
  },
  {
    "name": "Vanderbilt University",
    "slug": "vanderbilt",
    "state": "TN",
    "city": "Nashville",
    "region": "Southeast",
    "csRanking": 70,
    "tuitionInState": 60348,
    "tuitionOutOfState": 60348,
    "roomAndBoard": 18920,
    "acceptanceRate": 0.07,
    "enrollment": 13131,
    "graduationRate": 0.94,
    "medianEarnings6yr": 80500,
    "medianDebt": 12500,
    "website": "https://www.vanderbilt.edu",
    "usnewsUrl": "https://www.usnews.com/best-colleges/vanderbilt-3535",
    "nicheGrades": {
      "overall": "A+",
      "academics": "A+",
      "value": "A",
      "diversity": "A",
      "campus": "A+",
      "athletics": "A",
      "partyScene": "A",
      "professors": "A+",
      "location": "A+",
      "dorms": "A",
      "campusFood": "A",
      "studentLife": "A+",
      "safety": "A+"
    },
    "nicheUrl": "https://www.niche.com/colleges/vanderbilt-university/"
  },
  {
    "name": "Emory University",
    "slug": "emory",
    "state": "GA",
    "city": "Atlanta",
    "region": "Southeast",
    "csRanking": 83,
    "tuitionInState": 57948,
    "tuitionOutOfState": 57948,
    "roomAndBoard": 16504,
    "acceptanceRate": 0.11,
    "enrollment": 15063,
    "graduationRate": 0.91,
    "medianEarnings6yr": 72800,
    "medianDebt": 13500,
    "website": "https://www.emory.edu",
    "usnewsUrl": "https://www.usnews.com/best-colleges/emory-1564",
    "nicheGrades": {
      "overall": "A+",
      "academics": "A+",
      "value": "A",
      "diversity": "A+",
      "campus": "A",
      "athletics": "B",
      "partyScene": "B+",
      "professors": "A+",
      "location": "A",
      "dorms": "A-",
      "campusFood": "A-",
      "studentLife": "A",
      "safety": "A"
    },
    "nicheUrl": "https://www.niche.com/colleges/emory-university/"
  },
  {
    "name": "Johns Hopkins University",
    "slug": "johns-hopkins",
    "state": "MD",
    "city": "Baltimore",
    "region": "Mid-Atlantic",
    "csRanking": 42,
    "tuitionInState": 60480,
    "tuitionOutOfState": 60480,
    "roomAndBoard": 18100,
    "acceptanceRate": 0.07,
    "enrollment": 26409,
    "graduationRate": 0.95,
    "medianEarnings6yr": 82400,
    "medianDebt": 14500,
    "website": "https://www.jhu.edu",
    "usnewsUrl": "https://www.usnews.com/best-colleges/jhu-2077",
    "nicheGrades": {
      "overall": "A+",
      "academics": "A+",
      "value": "A",
      "diversity": "A",
      "campus": "A",
      "athletics": "B+",
      "partyScene": "B",
      "professors": "A+",
      "location": "A-",
      "dorms": "A-",
      "campusFood": "A-",
      "studentLife": "A",
      "safety": "B"
    },
    "nicheUrl": "https://www.niche.com/colleges/johns-hopkins-university/"
  },
  {
    "name": "University of Virginia",
    "slug": "uva",
    "state": "VA",
    "city": "Charlottesville",
    "region": "Mid-Atlantic",
    "csRanking": 27,
    "tuitionInState": 18584,
    "tuitionOutOfState": 52218,
    "roomAndBoard": 12948,
    "acceptanceRate": 0.18,
    "enrollment": 25042,
    "graduationRate": 0.95,
    "medianEarnings6yr": 74600,
    "medianDebt": 12500,
    "website": "https://www.virginia.edu",
    "usnewsUrl": "https://www.usnews.com/best-colleges/university-of-virginia-3744",
    "nicheGrades": {
      "overall": "A+",
      "academics": "A+",
      "value": "A+",
      "diversity": "A",
      "campus": "A+",
      "athletics": "A",
      "partyScene": "A",
      "professors": "A+",
      "location": "A+",
      "dorms": "A",
      "campusFood": "A-",
      "studentLife": "A+",
      "safety": "A+"
    },
    "nicheUrl": "https://www.niche.com/colleges/university-of-virginia/"
  },
  {
    "name": "University of Notre Dame",
    "slug": "notre-dame",
    "state": "IN",
    "city": "Notre Dame",
    "region": "Midwest",
    "csRanking": 59,
    "tuitionInState": 60301,
    "tuitionOutOfState": 60301,
    "roomAndBoard": 16996,
    "acceptanceRate": 0.13,
    "enrollment": 12607,
    "graduationRate": 0.97,
    "medianEarnings6yr": 76200,
    "medianDebt": 13500,
    "website": "https://www.nd.edu",
    "usnewsUrl": "https://www.usnews.com/best-colleges/notre-dame-1840",
    "nicheGrades": {
      "overall": "A+",
      "academics": "A+",
      "value": "A",
      "diversity": "B+",
      "campus": "A+",
      "athletics": "A+",
      "partyScene": "B+",
      "professors": "A+",
      "location": "B+",
      "dorms": "A+",
      "campusFood": "A",
      "studentLife": "A+",
      "safety": "A+"
    },
    "nicheUrl": "https://www.niche.com/colleges/university-of-notre-dame/"
  },
  {
    "name": "Tufts University",
    "slug": "tufts",
    "state": "MA",
    "city": "Medford",
    "region": "Northeast",
    "csRanking": 70,
    "tuitionInState": 65016,
    "tuitionOutOfState": 65016,
    "roomAndBoard": 17660,
    "acceptanceRate": 0.11,
    "enrollment": 12020,
    "graduationRate": 0.94,
    "medianEarnings6yr": 73200,
    "medianDebt": 13000,
    "website": "https://www.tufts.edu",
    "usnewsUrl": "https://www.usnews.com/best-colleges/tufts-2219",
    "nicheGrades": {
      "overall": "A+",
      "academics": "A+",
      "value": "A",
      "diversity": "A",
      "campus": "A",
      "athletics": "B+",
      "partyScene": "B+",
      "professors": "A+",
      "location": "A+",
      "dorms": "A-",
      "campusFood": "A-",
      "studentLife": "A",
      "safety": "A"
    },
    "nicheUrl": "https://www.niche.com/colleges/tufts-university/"
  },
  {
    "name": "Lehigh University",
    "slug": "lehigh",
    "state": "PA",
    "city": "Bethlehem",
    "region": "Mid-Atlantic",
    "csRanking": 97,
    "tuitionInState": 62110,
    "tuitionOutOfState": 62110,
    "roomAndBoard": 14680,
    "acceptanceRate": 0.47,
    "enrollment": 7236,
    "graduationRate": 0.89,
    "medianEarnings6yr": 74500,
    "medianDebt": 18500,
    "website": "https://www.lehigh.edu",
    "usnewsUrl": "https://www.usnews.com/best-colleges/lehigh-3289",
    "nicheGrades": {
      "overall": "A",
      "academics": "A",
      "value": "B+",
      "diversity": "B+",
      "campus": "A",
      "athletics": "A",
      "partyScene": "A",
      "professors": "A",
      "location": "B+",
      "dorms": "A-",
      "campusFood": "A-",
      "studentLife": "A",
      "safety": "A"
    },
    "nicheUrl": "https://www.niche.com/colleges/lehigh-university/"
  },
  {
    "name": "University of Rochester",
    "slug": "rochester",
    "state": "NY",
    "city": "Rochester",
    "region": "Northeast",
    "csRanking": 59,
    "tuitionInState": 62690,
    "tuitionOutOfState": 62690,
    "roomAndBoard": 17520,
    "acceptanceRate": 0.29,
    "enrollment": 11990,
    "graduationRate": 0.9,
    "medianEarnings6yr": 72800,
    "medianDebt": 16500,
    "website": "https://www.rochester.edu",
    "usnewsUrl": "https://www.usnews.com/best-colleges/university-of-rochester-2894",
    "nicheGrades": {
      "overall": "A",
      "academics": "A+",
      "value": "B+",
      "diversity": "A",
      "campus": "A",
      "athletics": "B+",
      "partyScene": "B",
      "professors": "A+",
      "location": "B",
      "dorms": "A-",
      "campusFood": "A-",
      "studentLife": "A",
      "safety": "A"
    },
    "nicheUrl": "https://www.niche.com/colleges/university-of-rochester/"
  },
  {
    "name": "Case Western Reserve University",
    "slug": "case-western",
    "state": "OH",
    "city": "Cleveland",
    "region": "Midwest",
    "csRanking": 107,
    "tuitionInState": 57498,
    "tuitionOutOfState": 57498,
    "roomAndBoard": 16370,
    "acceptanceRate": 0.27,
    "enrollment": 11955,
    "graduationRate": 0.87,
    "medianEarnings6yr": 74000,
    "medianDebt": 19000,
    "website": "https://www.case.edu",
    "usnewsUrl": "https://www.usnews.com/best-colleges/case-western-1467",
    "nicheGrades": {
      "overall": "A",
      "academics": "A+",
      "value": "B+",
      "diversity": "A",
      "campus": "B+",
      "athletics": "B",
      "partyScene": "B-",
      "professors": "A+",
      "location": "B+",
      "dorms": "B+",
      "campusFood": "B",
      "studentLife": "B+",
      "safety": "B+"
    },
    "nicheUrl": "https://www.niche.com/colleges/case-western-reserve-university/"
  },
  {
    "name": "George Washington University",
    "slug": "gwu",
    "state": "DC",
    "city": "Washington",
    "region": "Mid-Atlantic",
    "csRanking": 97,
    "tuitionInState": 60856,
    "tuitionOutOfState": 60856,
    "roomAndBoard": 16792,
    "acceptanceRate": 0.41,
    "enrollment": 26828,
    "graduationRate": 0.84,
    "medianEarnings6yr": 72000,
    "medianDebt": 22000,
    "website": "https://www.gwu.edu",
    "usnewsUrl": "https://www.usnews.com/best-colleges/gwu-1997",
    "nicheGrades": {
      "overall": "A",
      "academics": "A",
      "value": "B",
      "diversity": "A+",
      "campus": "A",
      "athletics": "B",
      "partyScene": "A",
      "professors": "A",
      "location": "A+",
      "dorms": "B+",
      "campusFood": "B+",
      "studentLife": "A",
      "safety": "B+"
    },
    "nicheUrl": "https://www.niche.com/colleges/george-washington-university/"
  },
  {
    "name": "University of Illinois Chicago",
    "slug": "uic",
    "state": "IL",
    "city": "Chicago",
    "region": "Midwest",
    "csRanking": 42,
    "tuitionInState": 10584,
    "tuitionOutOfState": 25064,
    "roomAndBoard": 14600,
    "acceptanceRate": 0.8,
    "enrollment": 32872,
    "graduationRate": 0.61,
    "medianEarnings6yr": 61500,
    "medianDebt": 13000,
    "website": "https://www.uic.edu",
    "usnewsUrl": "https://www.usnews.com/best-colleges/uic-1776",
    "nicheGrades": {
      "overall": "A",
      "academics": "A",
      "value": "A+",
      "diversity": "A+",
      "campus": "B+",
      "athletics": "B",
      "partyScene": "B",
      "professors": "A",
      "location": "A+",
      "dorms": "B",
      "campusFood": "B",
      "studentLife": "B+",
      "safety": "B"
    },
    "nicheUrl": "https://www.niche.com/colleges/university-of-illinois-chicago/"
  },
  {
    "name": "University of Connecticut",
    "slug": "uconn",
    "state": "CT",
    "city": "Storrs",
    "region": "Northeast",
    "csRanking": 63,
    "tuitionInState": 18618,
    "tuitionOutOfState": 40378,
    "roomAndBoard": 14500,
    "acceptanceRate": 0.54,
    "enrollment": 32257,
    "graduationRate": 0.84,
    "medianEarnings6yr": 67500,
    "medianDebt": 14000,
    "website": "https://www.uconn.edu",
    "usnewsUrl": "https://www.usnews.com/best-colleges/uconn-1418",
    "nicheGrades": {
      "overall": "A",
      "academics": "A",
      "value": "A+",
      "diversity": "A",
      "campus": "A",
      "athletics": "A",
      "partyScene": "A",
      "professors": "A",
      "location": "B+",
      "dorms": "B+",
      "campusFood": "B+",
      "studentLife": "A",
      "safety": "A"
    },
    "nicheUrl": "https://www.niche.com/colleges/university-of-connecticut/"
  },
  {
    "name": "University of Delaware",
    "slug": "delaware",
    "state": "DE",
    "city": "Newark",
    "region": "Mid-Atlantic",
    "csRanking": 70,
    "tuitionInState": 14950,
    "tuitionOutOfState": 36300,
    "roomAndBoard": 13500,
    "acceptanceRate": 0.7,
    "enrollment": 24000,
    "graduationRate": 0.81,
    "medianEarnings6yr": 65500,
    "medianDebt": 15000,
    "website": "https://www.udel.edu",
    "usnewsUrl": "https://www.usnews.com/best-colleges/university-of-delaware-1431",
    "nicheGrades": {
      "overall": "A",
      "academics": "A",
      "value": "A+",
      "diversity": "B+",
      "campus": "A",
      "athletics": "A",
      "partyScene": "A",
      "professors": "A",
      "location": "A",
      "dorms": "B+",
      "campusFood": "B+",
      "studentLife": "A",
      "safety": "A"
    },
    "nicheUrl": "https://www.niche.com/colleges/university-of-delaware/"
  },
  {
    "name": "Dartmouth College",
    "slug": "dartmouth",
    "state": "NH",
    "city": "Hanover",
    "region": "Northeast",
    "csRanking": 63,
    "tuitionInState": 62430,
    "tuitionOutOfState": 62430,
    "roomAndBoard": 17820,
    "acceptanceRate": 0.07,
    "enrollment": 6789,
    "graduationRate": 0.96,
    "medianEarnings6yr": 83200,
    "medianDebt": 12500,
    "website": "https://www.dartmouth.edu",
    "usnewsUrl": "https://www.usnews.com/best-colleges/dartmouth-2573",
    "nicheGrades": {
      "overall": "A+",
      "academics": "A+",
      "value": "A",
      "diversity": "A",
      "campus": "A+",
      "athletics": "A",
      "partyScene": "A",
      "professors": "A+",
      "location": "B+",
      "dorms": "A",
      "campusFood": "A",
      "studentLife": "A+",
      "safety": "A+"
    },
    "nicheUrl": "https://www.niche.com/colleges/dartmouth-college/"
  },
  {
    "name": "University of Iowa",
    "slug": "iowa",
    "state": "IA",
    "city": "Iowa City",
    "region": "Midwest",
    "csRanking": 97,
    "tuitionInState": 9646,
    "tuitionOutOfState": 31569,
    "roomAndBoard": 11390,
    "acceptanceRate": 0.85,
    "enrollment": 31656,
    "graduationRate": 0.72,
    "medianEarnings6yr": 60200,
    "medianDebt": 14000,
    "website": "https://www.uiowa.edu",
    "usnewsUrl": "https://www.usnews.com/best-colleges/university-of-iowa-1892",
    "nicheGrades": {
      "overall": "A",
      "academics": "A",
      "value": "A+",
      "diversity": "B+",
      "campus": "A",
      "athletics": "A",
      "partyScene": "A",
      "professors": "A",
      "location": "A",
      "dorms": "B+",
      "campusFood": "B+",
      "studentLife": "A",
      "safety": "A"
    },
    "nicheUrl": "https://www.niche.com/colleges/university-of-iowa/"
  },
  {
    "name": "Tulane University",
    "slug": "tulane",
    "state": "LA",
    "city": "New Orleans",
    "region": "Southeast",
    "csRanking": 83,
    "tuitionInState": 61196,
    "tuitionOutOfState": 61196,
    "roomAndBoard": 16760,
    "acceptanceRate": 0.13,
    "enrollment": 13800,
    "graduationRate": 0.82,
    "medianEarnings6yr": 67000,
    "medianDebt": 17000,
    "website": "https://www.tulane.edu",
    "usnewsUrl": "https://www.usnews.com/best-colleges/tulane-2029",
    "nicheGrades": {
      "overall": "A+",
      "academics": "A",
      "value": "B",
      "diversity": "A",
      "campus": "A+",
      "athletics": "B+",
      "partyScene": "A+",
      "professors": "A",
      "location": "A+",
      "dorms": "A-",
      "campusFood": "A-",
      "studentLife": "A+",
      "safety": "B"
    },
    "nicheUrl": "https://www.niche.com/colleges/tulane-university/"
  },
  {
    "name": "University of Tennessee",
    "slug": "utk",
    "state": "TN",
    "city": "Knoxville",
    "region": "Southeast",
    "csRanking": 89,
    "tuitionInState": 13244,
    "tuitionOutOfState": 31640,
    "roomAndBoard": 11530,
    "acceptanceRate": 0.71,
    "enrollment": 30530,
    "graduationRate": 0.7,
    "medianEarnings6yr": 58200,
    "medianDebt": 13500,
    "website": "https://www.utk.edu",
    "usnewsUrl": "https://www.usnews.com/best-colleges/university-of-tennessee-3530",
    "nicheGrades": {
      "overall": "A",
      "academics": "A",
      "value": "A+",
      "diversity": "B+",
      "campus": "A+",
      "athletics": "A+",
      "partyScene": "A",
      "professors": "A",
      "location": "A",
      "dorms": "B+",
      "campusFood": "B+",
      "studentLife": "A+",
      "safety": "A"
    },
    "nicheUrl": "https://www.niche.com/colleges/university-of-tennessee-knoxville/"
  },
  {
    "name": "University of Nebraska-Lincoln",
    "slug": "unl",
    "state": "NE",
    "city": "Lincoln",
    "region": "Midwest",
    "csRanking": 107,
    "tuitionInState": 9742,
    "tuitionOutOfState": 26228,
    "roomAndBoard": 11350,
    "acceptanceRate": 0.77,
    "enrollment": 25006,
    "graduationRate": 0.67,
    "medianEarnings6yr": 59500,
    "medianDebt": 14000,
    "website": "https://www.unl.edu",
    "usnewsUrl": "https://www.usnews.com/best-colleges/unl-2536",
    "nicheGrades": {
      "overall": "A",
      "academics": "A",
      "value": "A+",
      "diversity": "B+",
      "campus": "A",
      "athletics": "A",
      "partyScene": "B+",
      "professors": "A",
      "location": "B+",
      "dorms": "B+",
      "campusFood": "B+",
      "studentLife": "A",
      "safety": "A"
    },
    "nicheUrl": "https://www.niche.com/colleges/university-of-nebraska-lincoln/"
  },
  {
    "name": "Kansas State University",
    "slug": "kstate",
    "state": "KS",
    "city": "Manhattan",
    "region": "Midwest",
    "csRanking": 156,
    "tuitionInState": 9531,
    "tuitionOutOfState": 24830,
    "roomAndBoard": 9290,
    "acceptanceRate": 0.95,
    "enrollment": 21000,
    "graduationRate": 0.65,
    "medianEarnings6yr": 56800,
    "medianDebt": 14500,
    "website": "https://www.k-state.edu",
    "usnewsUrl": "https://www.usnews.com/best-colleges/ksu-1952",
    "nicheGrades": {
      "overall": "A",
      "academics": "A",
      "value": "A+",
      "diversity": "B",
      "campus": "A",
      "athletics": "A",
      "partyScene": "B+",
      "professors": "A",
      "location": "B",
      "dorms": "B",
      "campusFood": "B",
      "studentLife": "A",
      "safety": "A"
    },
    "nicheUrl": "https://www.niche.com/colleges/kansas-state-university/"
  },
  {
    "name": "University of Kansas",
    "slug": "ku",
    "state": "KS",
    "city": "Lawrence",
    "region": "Midwest",
    "csRanking": 117,
    "tuitionInState": 10092,
    "tuitionOutOfState": 26314,
    "roomAndBoard": 9800,
    "acceptanceRate": 0.93,
    "enrollment": 27468,
    "graduationRate": 0.64,
    "medianEarnings6yr": 57500,
    "medianDebt": 14000,
    "website": "https://www.ku.edu",
    "usnewsUrl": "https://www.usnews.com/best-colleges/university-of-kansas-1948",
    "nicheGrades": {
      "overall": "A",
      "academics": "A",
      "value": "A+",
      "diversity": "B+",
      "campus": "A",
      "athletics": "A",
      "partyScene": "A-",
      "professors": "A",
      "location": "A-",
      "dorms": "B+",
      "campusFood": "B+",
      "studentLife": "A",
      "safety": "A"
    },
    "nicheUrl": "https://www.niche.com/colleges/university-of-kansas/"
  },
  {
    "name": "Texas A&M University",
    "slug": "tamu",
    "state": "TX",
    "city": "College Station",
    "region": "Southwest",
    "csRanking": 33,
    "tuitionInState": 13239,
    "tuitionOutOfState": 39513,
    "roomAndBoard": 10600,
    "acceptanceRate": 0.63,
    "enrollment": 74000,
    "graduationRate": 0.82,
    "medianEarnings6yr": 68500,
    "medianDebt": 12000,
    "website": "https://www.tamu.edu",
    "usnewsUrl": "https://www.usnews.com/best-colleges/texas-am-3578",
    "nicheGrades": {
      "overall": "A+",
      "academics": "A",
      "value": "A+",
      "diversity": "A",
      "campus": "A+",
      "athletics": "A+",
      "partyScene": "A-",
      "professors": "A",
      "location": "B+",
      "dorms": "B+",
      "campusFood": "B+",
      "studentLife": "A+",
      "safety": "A"
    },
    "nicheUrl": "https://www.niche.com/colleges/texas-a-and-m-university/"
  },
  {
    "name": "University of North Carolina Chapel Hill",
    "slug": "unc",
    "state": "NC",
    "city": "Chapel Hill",
    "region": "Southeast",
    "csRanking": 42,
    "tuitionInState": 7020,
    "tuitionOutOfState": 36082,
    "roomAndBoard": 12628,
    "acceptanceRate": 0.19,
    "enrollment": 32006,
    "graduationRate": 0.91,
    "medianEarnings6yr": 67500,
    "medianDebt": 11000,
    "website": "https://www.unc.edu",
    "usnewsUrl": "https://www.usnews.com/best-colleges/unc-2974",
    "nicheGrades": {
      "overall": "A+",
      "academics": "A+",
      "value": "A+",
      "diversity": "A",
      "campus": "A+",
      "athletics": "A+",
      "partyScene": "A",
      "professors": "A+",
      "location": "A+",
      "dorms": "A-",
      "campusFood": "A-",
      "studentLife": "A+",
      "safety": "A"
    },
    "nicheUrl": "https://www.niche.com/colleges/university-of-north-carolina-at-chapel-hill/"
  },
  {
    "name": "University of California Riverside",
    "slug": "ucr",
    "state": "CA",
    "city": "Riverside",
    "region": "West",
    "csRanking": 28,
    "tuitionInState": 13827,
    "tuitionOutOfState": 43779,
    "roomAndBoard": 18400,
    "acceptanceRate": 0.66,
    "enrollment": 25547,
    "graduationRate": 0.76,
    "medianEarnings6yr": 62500,
    "medianDebt": 10500,
    "website": "https://www.ucr.edu",
    "usnewsUrl": "https://www.usnews.com/best-colleges/ucr-1316",
    "nicheGrades": {
      "overall": "A",
      "academics": "A",
      "value": "A+",
      "diversity": "A+",
      "campus": "B+",
      "athletics": "B",
      "partyScene": "B",
      "professors": "A",
      "location": "B+",
      "dorms": "B+",
      "campusFood": "B",
      "studentLife": "A",
      "safety": "A"
    },
    "nicheUrl": "https://www.niche.com/colleges/university-of-california-riverside/"
  },
  {
    "name": "Temple University",
    "slug": "temple",
    "state": "PA",
    "city": "Philadelphia",
    "region": "Mid-Atlantic",
    "csRanking": 89,
    "tuitionInState": 18048,
    "tuitionOutOfState": 29736,
    "roomAndBoard": 14000,
    "acceptanceRate": 0.67,
    "enrollment": 34000,
    "graduationRate": 0.7,
    "medianEarnings6yr": 60500,
    "medianDebt": 16500,
    "website": "https://www.temple.edu",
    "usnewsUrl": "https://www.usnews.com/best-colleges/temple-3371",
    "nicheGrades": {
      "overall": "A",
      "academics": "A",
      "value": "A+",
      "diversity": "A",
      "campus": "B+",
      "athletics": "A",
      "partyScene": "A",
      "professors": "A",
      "location": "A+",
      "dorms": "B",
      "campusFood": "B",
      "studentLife": "A",
      "safety": "B"
    },
    "nicheUrl": "https://www.niche.com/colleges/temple-university/"
  },
  {
    "name": "Colorado State University",
    "slug": "csu",
    "state": "CO",
    "city": "Fort Collins",
    "region": "West",
    "csRanking": 97,
    "tuitionInState": 12482,
    "tuitionOutOfState": 31362,
    "roomAndBoard": 12700,
    "acceptanceRate": 0.8,
    "enrollment": 33877,
    "graduationRate": 0.71,
    "medianEarnings6yr": 61800,
    "medianDebt": 14000,
    "website": "https://www.colostate.edu",
    "usnewsUrl": "https://www.usnews.com/best-colleges/colorado-state-1350",
    "nicheGrades": {
      "overall": "A",
      "academics": "A",
      "value": "A+",
      "diversity": "B+",
      "campus": "A",
      "athletics": "A",
      "partyScene": "A-",
      "professors": "A",
      "location": "A",
      "dorms": "B+",
      "campusFood": "B+",
      "studentLife": "A",
      "safety": "A"
    },
    "nicheUrl": "https://www.niche.com/colleges/colorado-state-university/"
  },
  {
    "name": "University of South Florida",
    "slug": "usf",
    "state": "FL",
    "city": "Tampa",
    "region": "Southeast",
    "csRanking": 80,
    "tuitionInState": 6410,
    "tuitionOutOfState": 17324,
    "roomAndBoard": 10050,
    "acceptanceRate": 0.44,
    "enrollment": 50644,
    "graduationRate": 0.72,
    "medianEarnings6yr": 57500,
    "medianDebt": 11500,
    "website": "https://www.usf.edu",
    "usnewsUrl": "https://www.usnews.com/best-colleges/usf-1537",
    "nicheGrades": {
      "overall": "A",
      "academics": "A",
      "value": "A+",
      "diversity": "A+",
      "campus": "A",
      "athletics": "A",
      "partyScene": "B+",
      "professors": "A",
      "location": "A",
      "dorms": "B",
      "campusFood": "B",
      "studentLife": "A",
      "safety": "B+"
    },
    "nicheUrl": "https://www.niche.com/colleges/university-of-south-florida/"
  },
  {
    "name": "North Carolina A&T State University",
    "slug": "ncat",
    "state": "NC",
    "city": "Greensboro",
    "region": "Southeast",
    "csRanking": null,
    "tuitionInState": 7178,
    "tuitionOutOfState": 19888,
    "roomAndBoard": 9500,
    "acceptanceRate": 0.54,
    "enrollment": 14000,
    "graduationRate": 0.55,
    "medianEarnings6yr": 56800,
    "medianDebt": 20000,
    "website": "https://www.ncat.edu",
    "usnewsUrl": "https://www.usnews.com/best-colleges/ncat-2969",
    "nicheGrades": {
      "overall": "B+",
      "academics": "B+",
      "value": "A",
      "diversity": "A+",
      "campus": "B+",
      "athletics": "A",
      "partyScene": "B+",
      "professors": "B+",
      "location": "B+",
      "dorms": "B",
      "campusFood": "B",
      "studentLife": "B+",
      "safety": "B+"
    },
    "nicheUrl": "https://www.niche.com/colleges/north-carolina-a-and-t-state-university/"
  },
  {
    "name": "Illinois Institute of Technology",
    "slug": "iit",
    "state": "IL",
    "city": "Chicago",
    "region": "Midwest",
    "csRanking": 97,
    "tuitionInState": 50262,
    "tuitionOutOfState": 50262,
    "roomAndBoard": 14700,
    "acceptanceRate": 0.64,
    "enrollment": 7878,
    "graduationRate": 0.73,
    "medianEarnings6yr": 68800,
    "medianDebt": 20500,
    "website": "https://www.iit.edu",
    "usnewsUrl": "https://www.usnews.com/best-colleges/iit-1691",
    "nicheGrades": {
      "overall": "B+",
      "academics": "A",
      "value": "B",
      "diversity": "A+",
      "campus": "B",
      "athletics": "C",
      "partyScene": "C",
      "professors": "A",
      "location": "A+",
      "dorms": "B",
      "campusFood": "B-",
      "studentLife": "B",
      "safety": "B"
    },
    "nicheUrl": "https://www.niche.com/colleges/illinois-institute-of-technology/"
  },
  {
    "name": "Baylor University",
    "slug": "baylor",
    "state": "TX",
    "city": "Waco",
    "region": "Southwest",
    "csRanking": 156,
    "tuitionInState": 50000,
    "tuitionOutOfState": 50000,
    "roomAndBoard": 14900,
    "acceptanceRate": 0.62,
    "enrollment": 19226,
    "graduationRate": 0.8,
    "medianEarnings6yr": 62500,
    "medianDebt": 20000,
    "website": "https://www.baylor.edu",
    "usnewsUrl": "https://www.usnews.com/best-colleges/baylor-3548",
    "nicheGrades": {
      "overall": "A",
      "academics": "A",
      "value": "B+",
      "diversity": "B+",
      "campus": "A+",
      "athletics": "A",
      "partyScene": "B",
      "professors": "A",
      "location": "B",
      "dorms": "A",
      "campusFood": "A",
      "studentLife": "A+",
      "safety": "A+"
    },
    "nicheUrl": "https://www.niche.com/colleges/baylor-university/"
  },
  {
    "name": "Auburn University",
    "slug": "auburn",
    "state": "AL",
    "city": "Auburn",
    "region": "Southeast",
    "csRanking": 117,
    "tuitionInState": 11378,
    "tuitionOutOfState": 30604,
    "roomAndBoard": 12164,
    "acceptanceRate": 0.74,
    "enrollment": 31785,
    "graduationRate": 0.74,
    "medianEarnings6yr": 62200,
    "medianDebt": 16000,
    "website": "https://www.auburn.edu",
    "usnewsUrl": "https://www.usnews.com/best-colleges/auburn-1002",
    "nicheGrades": {
      "overall": "A",
      "academics": "A",
      "value": "A+",
      "diversity": "B+",
      "campus": "A+",
      "athletics": "A+",
      "partyScene": "A",
      "professors": "A",
      "location": "B+",
      "dorms": "B+",
      "campusFood": "B+",
      "studentLife": "A+",
      "safety": "A"
    },
    "nicheUrl": "https://www.niche.com/colleges/auburn-university/"
  },
  {
    "name": "University of Kentucky",
    "slug": "uky",
    "state": "KY",
    "city": "Lexington",
    "region": "Southeast",
    "csRanking": 117,
    "tuitionInState": 13068,
    "tuitionOutOfState": 30996,
    "roomAndBoard": 10700,
    "acceptanceRate": 0.96,
    "enrollment": 30700,
    "graduationRate": 0.65,
    "medianEarnings6yr": 56800,
    "medianDebt": 14500,
    "website": "https://www.uky.edu",
    "usnewsUrl": "https://www.usnews.com/best-colleges/university-of-kentucky-1967",
    "nicheGrades": {
      "overall": "A",
      "academics": "A",
      "value": "A+",
      "diversity": "B+",
      "campus": "A",
      "athletics": "A+",
      "partyScene": "A-",
      "professors": "A",
      "location": "A",
      "dorms": "B+",
      "campusFood": "B+",
      "studentLife": "A",
      "safety": "A"
    },
    "nicheUrl": "https://www.niche.com/colleges/university-of-kentucky/"
  },
  {
    "name": "University of Missouri",
    "slug": "mizzou",
    "state": "MO",
    "city": "Columbia",
    "region": "Midwest",
    "csRanking": 138,
    "tuitionInState": 10452,
    "tuitionOutOfState": 27924,
    "roomAndBoard": 11800,
    "acceptanceRate": 0.76,
    "enrollment": 30016,
    "graduationRate": 0.72,
    "medianEarnings6yr": 57200,
    "medianDebt": 15000,
    "website": "https://www.missouri.edu",
    "usnewsUrl": "https://www.usnews.com/best-colleges/university-of-missouri-2516",
    "nicheGrades": {
      "overall": "A",
      "academics": "A",
      "value": "A+",
      "diversity": "B+",
      "campus": "A",
      "athletics": "A",
      "partyScene": "A-",
      "professors": "A",
      "location": "A",
      "dorms": "B+",
      "campusFood": "B+",
      "studentLife": "A",
      "safety": "A"
    },
    "nicheUrl": "https://www.niche.com/colleges/university-of-missouri/"
  },
  {
    "name": "Louisiana State University",
    "slug": "lsu",
    "state": "LA",
    "city": "Baton Rouge",
    "region": "Southeast",
    "csRanking": 107,
    "tuitionInState": 11962,
    "tuitionOutOfState": 29242,
    "roomAndBoard": 11360,
    "acceptanceRate": 0.75,
    "enrollment": 38013,
    "graduationRate": 0.67,
    "medianEarnings6yr": 55800,
    "medianDebt": 15500,
    "website": "https://www.lsu.edu",
    "usnewsUrl": "https://www.usnews.com/best-colleges/lsu-2010",
    "nicheGrades": {
      "overall": "A",
      "academics": "A",
      "value": "A+",
      "diversity": "A",
      "campus": "A+",
      "athletics": "A+",
      "partyScene": "A",
      "professors": "A",
      "location": "A",
      "dorms": "B+",
      "campusFood": "B+",
      "studentLife": "A+",
      "safety": "B+"
    },
    "nicheUrl": "https://www.niche.com/colleges/louisiana-state-university/"
  },
  {
    "name": "Oklahoma State University",
    "slug": "okstate",
    "state": "OK",
    "city": "Stillwater",
    "region": "Southwest",
    "csRanking": 176,
    "tuitionInState": 9074,
    "tuitionOutOfState": 24212,
    "roomAndBoard": 9900,
    "acceptanceRate": 0.72,
    "enrollment": 25000,
    "graduationRate": 0.66,
    "medianEarnings6yr": 57500,
    "medianDebt": 15000,
    "website": "https://go.okstate.edu",
    "usnewsUrl": "https://www.usnews.com/best-colleges/oklahoma-state-3170",
    "nicheGrades": {
      "overall": "A",
      "academics": "A",
      "value": "A+",
      "diversity": "B+",
      "campus": "A",
      "athletics": "A",
      "partyScene": "B+",
      "professors": "A",
      "location": "B",
      "dorms": "B+",
      "campusFood": "B+",
      "studentLife": "A",
      "safety": "A"
    },
    "nicheUrl": "https://www.niche.com/colleges/oklahoma-state-university/"
  },
  {
    "name": "University of Oklahoma",
    "slug": "ou",
    "state": "OK",
    "city": "Norman",
    "region": "Southwest",
    "csRanking": 117,
    "tuitionInState": 9957,
    "tuitionOutOfState": 26460,
    "roomAndBoard": 10420,
    "acceptanceRate": 0.72,
    "enrollment": 27731,
    "graduationRate": 0.69,
    "medianEarnings6yr": 57000,
    "medianDebt": 15500,
    "website": "https://www.ou.edu",
    "usnewsUrl": "https://www.usnews.com/best-colleges/university-of-oklahoma-3184",
    "nicheGrades": {
      "overall": "A",
      "academics": "A",
      "value": "A+",
      "diversity": "B+",
      "campus": "A",
      "athletics": "A+",
      "partyScene": "A-",
      "professors": "A",
      "location": "A",
      "dorms": "B+",
      "campusFood": "B+",
      "studentLife": "A",
      "safety": "A"
    },
    "nicheUrl": "https://www.niche.com/colleges/university-of-oklahoma/"
  },
  {
    "name": "University of Alabama",
    "slug": "alabama",
    "state": "AL",
    "city": "Tuscaloosa",
    "region": "Southeast",
    "csRanking": 138,
    "tuitionInState": 11780,
    "tuitionOutOfState": 30250,
    "roomAndBoard": 11210,
    "acceptanceRate": 0.8,
    "enrollment": 37665,
    "graduationRate": 0.73,
    "medianEarnings6yr": 54500,
    "medianDebt": 15000,
    "website": "https://www.ua.edu",
    "usnewsUrl": "https://www.usnews.com/best-colleges/university-of-alabama-1051",
    "nicheGrades": {
      "overall": "A",
      "academics": "A",
      "value": "A+",
      "diversity": "B+",
      "campus": "A+",
      "athletics": "A+",
      "partyScene": "A",
      "professors": "A",
      "location": "A",
      "dorms": "B+",
      "campusFood": "B+",
      "studentLife": "A+",
      "safety": "A"
    },
    "nicheUrl": "https://www.niche.com/colleges/the-university-of-alabama/"
  }
]
